<page>
    <title>全豪オープン</title>
    <ns>0</ns>
    <id>59946</id>
    <revision>
      <id>95554291</id>
      <parentid>94485667</parentid>
      <timestamp>2023-06-09T21:45:51Z</timestamp>
      <contributor>
        <username>Bcxfubot</username>
        <id>291984</id>
      </contributor>
      <minor />
      <comment>外部リンクの修正 http:// -&gt; https:// (www.nikkansports.com) ([[Wikipedia:Bot|Bot]]による編集)</comment>
      <model>wikitext</model>
      <format>text/x-wiki</format>
      <text bytes="22403" xml:space="preserve">{{テニスグランドスラム
| Name = 全豪オープン
| Current =
| Bar Color = #FFDD55
| City = [[メルボルン]]
| Country = {{AUS}}
| Venue = [[メルボルン・パーク]]
| Surface = 芝 (1905–87)&lt;br /&gt;ハード (1988–現在)&lt;ref group="注"&gt;リバウンドエース (1988–2007) — プレクシクッション (2008–19) — グリーンセット (2020–現在)&lt;/ref&gt;
| Men Draw = 128S / 128Q / 64D
| Women Draw = 128S / 96Q / 64D
| Prize Money = [[オーストラリアドル|A$]]71,000,000 (2020)&lt;ref&gt;{{cite web|url=https://ausopen.com/articles/news/record-71-million-prize-money-australian-open-2020|title=Record $71 million in prize money for Australian Open 2020|website=ausopen.com|accessdate=2019-12-27}}&lt;/ref&gt;
| Web site = https://ausopen.com/
| Notes =}}
[[ファイル:2017-01 Rod Laver Arena.jpg|right|200px|thumb|センターコートの「ロッド・レーバー・アリーナ」]]

'''全豪オープン'''（ぜんごうオープン、英語：''Australian Open''）は、毎年1月後半に[[オーストラリア]]の[[メルボルン]]で開催される[[テニス]]の[[グランドスラム (テニス)|4大国際大会]]の一つである。主催および運営は[[テニス・オーストラリア]]が行う。

== 概要 ==
会場の[[メルボルン・パーク]]には開閉式の屋根付き競技場である[[ロッド・レーバー・アリーナ]]を中心に、[[マーガレット・コート・アリーナ]]を含む{{要出典範囲|26面|date=2020年8月}}ものコートが整備されている。2000年にはサブアリーナとして[[ジョン・ケイン・アリーナ|ボーダフォン・アリーナ]]（現在のジョン・ケイン・アリーナ）が建設され、2015年にはマーガレット・コート・アリーナに開閉式屋根を設置する改修工事が完了し、3つの開閉式の屋根付きスタジアムを設けることになった。会場に開閉式の屋根を設置した大会は全豪オープンが最初である{{要出典|date=2020年8月}}。

男子シングルス部門の優勝者には[[ノーマン・ブルックス]]・チャレンジ・カップが、女子シングルス部門の優勝者には[[ダフネ・アクハースト]]・メモリアル・カップが&lt;!-- 、{{要出典範囲|其々の表彰式の際にオーストラリア名物であるコアラのぬいぐるみと共に|date=2020年8月}} --&gt;贈られる。&lt;!-- {{要出典範囲|2007年まではカンガルーのぬいぐるみが贈られており|date=2020年8月}}、これらは本大会ならではの光景となっている。 --&gt;

全豪オープンは、開催時期の変更も多い大会である。クーヨン・テニスクラブで開かれていた時代、1976年までは現在のような1月開催であったが、1977年には1月と12月の2回開催された。その後、1978年から1985年までは12月の年末に開催されていた。1987年から1月開催に戻り、1988年には会場がメルボルン・パークに移転して、現在に至っている。会場移転の決定による開催時期の変更により（1985年12月 → 1987年1月）、「1986年全豪オープン」は開催されなかった。
[[ファイル:Margaret Court Arena (Australian Open 2017).jpg|right|200px|thumb|マーガレット・コート・アリーナ]]
&lt;!-- == エクストリーム・ヒート・ポリシー ==
本大会は熱中症対策として「エクストリーム・ヒート・ポリシー」（英語：''Extreme Heat Policy, EHP''）と呼ばれる独自ルールが導入されている&lt;ref name="ehp"&gt;{{cite web|url=https://ausopen.com/visit/tournament-info/policies|title=Policies|website=ausopen.com|accessdate=2020-08-13}}&lt;/ref&gt;。外気温が35度を上回るか、湿球黒球温度が28度を上回った際に、主審が試合開始時間を遅らせることが出来る。条件を満たした場合、3つの開閉式屋根付スタジアムに関しては屋根を閉めて試合が行われる。

2019年からは「全豪オープン・ヒート・ストレス・スケール」（英語：''AO Heat Stress Scale, AO HSS''）と呼ばれるエクストリーム・ヒート・ポリシーの規定が新たに適用されている&lt;ref name="ehp" /&gt;。このスケールは1～5の5段階に分かれており、試合前や最初の2セットで4に達した場合、10分間の休憩が認められる&lt;ref group="注"&gt;女子シングルスでは第2セットと第3セットの間に、男子シングルスは第3セット終了後に10分間の休憩が認められる。&lt;/ref&gt;。また、5に達すると試合が中断されることがある&lt;ref&gt;{{cite web|url=https://www.afpbb.com/articles/-/3204552|title=「死にそうな暑さ」の全豪OP、新たな熱中症対策を導入|website=afpbb.com|date=2018-12-29|accessdate=2020-08-13}}&lt;/ref&gt;。 --&gt;
== 歴史 ==
[[File:Three Japanese tennis players 1932 in Sydney.jpg|thumb|1932年に出場した日本選手。中央左より[[佐藤次郎]]、[[原田武一]]、[[布井良助]]。佐藤は男子シングルスで準決勝進出、混合ダブルスで準優勝した]]
* [[1905年]] - オーストラリアと[[ニュージーランド]]の共同大会である「オーストラレージアン・テニス選手権」（Australasian Tennis Championship）として創設。男子シングルス・男子ダブルスの2部門のみで始まった。第1回の男子シングルスは[[ロドニー・ヒース]]（[[1884年]] - [[1936年]]）が優勝。
* [[1916年]] - [[1918年]] - [[第一次世界大戦]]のため、3年間大会開催中止。
* [[1922年]] - 女子シングルス・女子ダブルス・混合ダブルスの3部門を創設。第1回の女子シングルスは[[マーガレット・モールズワース]]（[[1894年]] - [[1985年]]）が優勝。
* [[1927年]] - 大会名を「オーストラリア選手権」と改称。
* [[1940年]] - この年は1月に大会が行われたが、[[第二次世界大戦]]のため[[1941年]]-[[1945年]]まで開催中止。
* [[1969年]] - オープン化され、「全豪オープン」となる。開催都市は持ち回りで行われた。
* [[1972年]] - メルボルンで固定開催することになり、クーヨン・テニスクラブがその会場となった。
* [[1988年]] - 会場をメルボルン・パーク（旧称フリンダース・パーク）に建設したナショナル・テニスセンターに移す。サーフェスも、グラスコートが廃止され、「リバウンド・エース」と呼ばれるハードコートになった。
* [[2002年]] - [[車いすテニス]]部門を創設。詳細は[[全豪オープン (車いすテニス)]]を参照。
* [[2008年]] - コート面をプレクシクッション ([[:en:Plexicushion]]) に変更。
* [[2019年]] - 最終セットに[[タイブレーク]]制を導入&lt;ref&gt;{{Cite web|url=https://www.afpbb.com/articles/-/3203716|title=全豪オープン、19年から最終セットにタイブレーク制導入|website=afpbb.com|accessdate=2019-12-27}}&lt;/ref&gt;。
* [[2020年]] - コート面をグリーンセット ([[:en:GreenSet]]) に変更&lt;ref&gt;{{Cite web|url=https://www.tennis.com.au/news/2019/07/26/greenset-worldwide-new-official-court-surface-supplier|title=GreenSet Worldwide new official court surface supplier|website=Tennis Australia|accessdate=2019-11-16}}&lt;/ref&gt;。
* [[2021年]] - [[新型コロナウイルス感染症の世界的流行 (2019年-)|新型コロナウイルス感染症の世界的流行]]により、14日間の検疫期間を確保するために、開催期間が[[2月8日]] - [[2月21日]]に変更された。また予選は[[1月10日]] - [[1月13日]]にかけて男子は[[ドーハ]]で、女子は[[ドバイ]]で行われた&lt;ref&gt;{{Cite news|title=全豪OP、2月8日開幕が正式決定「歴史的な大会に」|newspaper=AFPBB News|date=2020-12-19|url=https://www.afpbb.com/articles/-/3322247|accessdate=2021-12-28|agency=AFP}}&lt;/ref&gt;&lt;ref&gt;{{Cite web|url=https://www.atptour.com/en/news/atp-announces-updated-start-to-2021-calendar|title=ATP Announces Updated Start To 2021 Calendar|accessdate=2020-12-22|publisher=ATP Tour|date=2020-12-16|website=ATPTour.com}}&lt;/ref&gt;。

== テレビ放送 ==
オーストラリア国内では[[ナイン・ネットワーク]]で放映され&lt;ref&gt;{{cite web|url=https://amp.smh.com.au/business/companies/nine-secures-rights-to-the-2019-australian-open-tennis-from-seven-20180624-p4zndj.html|title=Nine secures rights to the 2019 Australian Open tennis from Seven|work=The Sydney Morning Herald|date=24 June 2018 |accessdate=2019-01-18}}&lt;/ref&gt;、男女シングルス決勝は現地時間で夜間に開催される。

2022年現在、日本国内では[[WOWOW]]で放送されている&lt;ref&gt;{{cite web|url=https://ausopen.com/broadcasters|title=Broadcast Partners|website=ausopen.com|accessdate=2020-08-13}}&lt;/ref&gt;。

衛星波については、WOWOWが開局直後の1992年より保有している&lt;ref&gt;{{cite web|url=https://toyokeizai.net/articles/-/229317?page=2|title=WOWOWが｢テニス中継｣に全力でこだわる理由 |website=toyokeizai.net|accessdate=2020-08-13}}&lt;/ref&gt;。{{要出典範囲|過去においては、地上波では[[テレビ東京]]による民放中継が2001年まで男女シングルス決勝戦のみ行われていたが、2002年以後は取りやめになった|date=2020年8月}}。さらにそれ以前は[[讀賣テレビ放送]]を制作局として[[日本テレビネットワーク協議会|日本テレビ系列]]向けに1988年から1991年まで放送していた&lt;ref&gt;{{Cite|和書|author=読売テレビ50年社史編纂委員会 編纂|title=読売テレビ50年社史|date=2009|pages=182}}&lt;/ref&gt;。2012年以降は[[日本放送協会]]（NHK）が一部試合の放送を行っていたが、2015年に地上波の放映権を獲得。原則として[[ミッドナイトチャンネル]]枠での録画中継となるが、[[錦織圭]]や[[大坂なおみ]]など日本人注目選手が出場する場合、生中継を実施している&lt;ref&gt;[http://www.hochi.co.jp/sports/ballsports/20141112-OHT1T50072.html 【テニス】全豪OP、NHKが放送権獲得へ] - スポーツ報知、2014年11月12日、同日閲覧&lt;/ref&gt;&lt;ref&gt;[https://www.nikkansports.com/sports/news/p-sp-tp0-20141112-1395159.html 錦織の全豪放送権をNHK獲得] - 日刊スポーツ、2014年11月12日、同日閲覧&lt;/ref&gt;。ただし、NHK総合のマルチ編成「[[マルチチャンネル|サブチャンネル]]」を活用して錦織圭/大坂なおみ選手の試合を中継することもある。&lt;ref group="注"&gt;NHKが放映権を持っている。ウィンブルドン選手権も同じ形態で行っている。&lt;/ref&gt;その後も2021年まで放送していた。

== 過去10年のシングルス優勝者 ==
{| class="wikitable" style="font-size: 95%;"
! 年 !! style="width: 25%;" | 男子 !! style="width: 25%;" | 女子 !! 備考
|-
! [[2014年全豪オープン|2014]]
| {{Flagicon|SUI}} [[スタニスラス・ワウリンカ]]||{{Flagicon|CHN}} [[李娜]]||ワウリンカは9年ぶりの[[BIG4 (テニス)|BIG4]]以外の優勝者。
|-
! [[2015年全豪オープン|2015]]
| {{Flagicon|SRB}} [[ノバク・ジョコビッチ]]||{{Flagicon|USA}} [[セリーナ・ウィリアムズ]]||[[ノバク・ジョコビッチ|ジョコビッチ]]は、オープン化以後では最多記録の優勝5回。ウィリアムズはオープン化以降では今大会最年長での優勝。
|-
! [[2016年全豪オープン|2016]]
| {{Flagicon|SRB}} [[ノバク・ジョコビッチ]]||{{Flagicon|DEU}} [[アンゲリク・ケルバー]]||ジョコビッチは史上最多タイの6度目の優勝。
|-
! [[2017年全豪オープン|2017]]
| {{Flagicon|SUI}} [[ロジャー・フェデラー]]||{{Flagicon|USA}} [[セリーナ・ウィリアムズ]]||フェデラーは7年ぶり5度目の優勝。ウィリアムズはオープン化以降歴代最多となる4大大会通算23度目の優勝。
|-
! [[2018年全豪オープン|2018]]
| {{Flagicon|SUI}} [[ロジャー・フェデラー]]||{{Flagicon|DEN}} [[キャロライン・ウォズニアッキ]]||フェデラーは2年連続史上最多タイの6度目の優勝、4大大会通算20勝。ウォズニアッキは4大大会初優勝。
|-
! [[2019年全豪オープン|2019]]
| {{Flagicon|SRB}} [[ノバク・ジョコビッチ]]||{{Flagicon|JPN}} [[大坂なおみ]]||大坂なおみはアジア勢で初の世界ランク1位となった。
|-
! [[2020年全豪オープン|2020]]
| {{Flagicon|SRB}} [[ノバク・ジョコビッチ]]||{{Flagicon|USA}} [[ソフィア・ケニン]]||ジョコビッチは史上最多の8度目の優勝。ケニンは4大大会初優勝。
|-
! [[2021年全豪オープン|2021]]
| {{Flagicon|SRB}} [[ノバク・ジョコビッチ]]||{{Flagicon|JPN}} [[大坂なおみ]]||ジョコビッチは3年連続9度目の優勝。大坂なおみは2度目の優勝。
|-
! [[2022年全豪オープン|2022]]
| {{Flagicon|ESP}} [[ラファエル・ナダル]]||{{Flagicon|AUS}} [[アシュリー・バーティ]]||ナダルは13年ぶり2回目の優勝、歴代最多となるGS21勝、ダブルキャリアグランドスラム達成。バーティは初優勝。
|-
! [[2023年全豪オープン|2023]]
| {{Flagicon|SRB}} [[ノバク・ジョコビッチ]]||{{Flagicon2|}} [[アリーナ・サバレンカ]]||ジョコビッチは史上最多10回目の優勝、歴代最多タイとなるGS22勝目。サバレンカはグランドスラム初優勝
|}

== 記録 ==
{| class="wikitable" style="font-size: 95%;"
|-
! 記録
! '''時代'''
! '''選手'''
! '''数'''
! 年
|-
|colspan=5|'''''男子 1905年以降'''''
|-
|rowspan=2| 男子シングルス最多優勝
||1967以前
| {{flagicon|AUS}} [[ロイ・エマーソン]]
| 6
| 1961, 1963-1967
|-
||1968以後
| {{flagicon|SER}} [[ノバク・ジョコビッチ]] 
| 10
| 2008, 2011-2013, 2015-2016, 2019-2021, 2023
|-
|rowspan=2|男子シングルス連覇記録
| 1967以前
| {{flagicon|AUS}} [[ロイ・エマーソン]]
| 5
| 1963-1967
|-
| 1968以後
| {{flagicon|SRB}} [[ノバク・ジョコビッチ]]
| 3
| 2011-2013、2019-2021
|-
|rowspan=2|男子ダブルス最多優勝
||1967以前
| {{flagicon|AUS}} [[エイドリアン・クイスト]]
| 10
| 1936-1940, 1946-1950
|-
||1968以後
| {{flagicon|USA}} [[ボブ・ブライアン]]&lt;br /&gt;{{flagicon|USA}} [[マイク・ブライアン]]
| 6
| 2006-2007, 2009-2011, 2013 &lt;br/&gt;2006-2007, 2009-2011, 2013
|-
|rowspan=2|男子ダブルス連覇記録
| 1967以前
| {{flagicon|AUS}} [[エイドリアン・クイスト]]
| 10
| 1936-1950
|-
| 1968以後
| {{flagicon|USA}} [[ボブ・ブライアン]]&lt;br /&gt;{{flagicon|USA}} [[マイク・ブライアン]]
| 3
| 2009-2011 &lt;br/&gt; 2009-2011
|-
|rowspan=2|男子混合ダブルス最多優勝
| 1967以前
| {{flagicon|AUS}} [[ハリー・ホップマン ]]&lt;br /&gt;{{flagicon|AUS}} [[コリン・ロング]]
| 4
| 1930, 1936-1937, 1939&lt;br /&gt;1940, 1946-1948
|-
| 1968以後
| {{flagicon|USA}} [[ジム・プー]]
| 3
| 1988-1990
|-
| rowspan="2" |男子最多優勝&lt;ref name=":0" group="注"&gt;シングルス・ダブルス・混合ダブルス合計。&lt;/ref&gt;
| 1967以前
| {{flagicon|AUS}} [[エイドリアン・クイスト]]
| 13
| 1936-1950 (3シングルス, 10ダブルス, 0混合)
|-
| 1968以後
| {{flagicon|SER}} [[ノバク・ジョコビッチ]]
| 10
| 2008-2023 (10シングルス, 0ダブルス, 0混合）
|-
|colspan=5|女子 '''''1922年以降'''''
|-
| rowspan="3" |女子シングルス最多優勝
|全体
| {{flagicon|AUS}} [[マーガレット・コート]]
|11
| 1960-1966, 1969-1971, 1973
|-
||1967以前
| {{flagicon|AUS}} [[マーガレット・コート]]
| 7
| 1960-1966
|-
|rowspan=2|1968以後
| {{flagicon|USA}} [[セリーナ・ウィリアムズ]]
| 7
| 2003, 2005, 2007, 2009-2010, 2015,2017
|-
| rowspan="3" |女子シングルス連覇記録
|-
| 1967以前
| {{flagicon|AUS}} [[マーガレット・コート]]
| 7
| 1960-1966
|-
| 1968以後
| {{flagicon|AUS}} [[マーガレット・コート]] &lt;br/&gt;{{flagicon|AUS}} [[イボンヌ・グーラゴング]] &lt;br/&gt; {{flagicon|GER}} [[シュテフィ・グラフ]]&lt;br/&gt;{{YUG}} [[モニカ・セレシュ]] &lt;br/&gt;{{flagicon|SUI}} [[マルチナ・ヒンギス]]
| 3
| 1969-1971 &lt;br/&gt;1974-1976 &lt;br/&gt;1988-1990 &lt;br/&gt;1991-1993 &lt;br/&gt;1997-1999
|-
| rowspan="3" |女子ダブルス最多優勝
|-
||1967以前
| {{flagicon|AUS}} [[テルマ・コイン・ロング]]
| 12
| 1936-1940, 1947, 1948-1949, 1951-1952, 1956, 1958
|-
| 1968以後
| {{flagicon|USA}} [[マルチナ・ナブラチロワ]]
| 8
| 1980, 1982-1985, 1987-1989
|-
| rowspan="3" |女子ダブルス連覇記録
|-
| 1967以前
| {{flagicon|AUS}} [[テルマ・コイン・ロング]] &lt;br/&gt;{{flagicon|AUS}} [[ナンシー・ウィン・ボルトン]]
| 5
| 1936-1940&lt;br/&gt;1936-1940
|-
| 1968以後
| {{flagicon|USA}} [[マルチナ・ナブラチロワ]]&lt;br /&gt;{{flagicon|USA}} [[パム・シュライバー]]
| 7
| 1982-1985, 1987-1989 &lt;br /&gt; 1982-1985, 1987-1989
|-
| rowspan="2" |女子混合ダブルス最多優勝
| 1967以前
| {{flagicon|AUS}} [[ダフネ・アクハースト]] &lt;br/&gt; {{flagicon|AUS}} [[ネル・ホール・ホップマン]]&lt;br /&gt;{{flagicon|AUS}} [[ナンシー・ウィン・ボルトン ]] &lt;br/&gt; {{flagicon|AUS}} [[テルマ・コイン・ロング]]
| 4
| 1924-1925, 1928-1929&lt;br/&gt;1930, 1936-1937, 1939&lt;br /&gt;1940, 1946-1948&lt;br/&gt; 1951-1952, 1954-1955
|-
| 1968以後
| {{flagicon|TCH}} [[ヤナ・ノボトナ]] &lt;br/&gt;{{flagicon|Latvia}} [[ラリサ・ネーランド]]
| 2
| 1988-1989&lt;br/&gt;1994-1996
|-
| rowspan="2" |女子最多優勝&lt;ref name=":0" group="注" /&gt;
| 1967以前
| {{flagicon|AUS}} [[ナンシー・ウィン・ボルトン]]
| 20
| 1936-1952 (6シングルス, 10ダブルス, 4混合)
|-
| 1968以後
| {{flagicon|USA}} [[マルチナ・ナブラチロワ]]
| 12
| 1980-2003 (3シングルス, 8ダブルス, 1混合)
|}

=== 優勝回数ランキング ===
{| class="wikitable" style="font-size: 95%;"
|-
!選手!!回数
|-
| {{flagicon|SRB}} '''[[ノバク・ジョコビッチ]]''' || 10
|-
| {{flagicon|AUS}} [[ロイ・エマーソン]] || rowspan="2" | 6
|-
| {{flagicon|SUI}} '''[[ロジャー・フェデラー]]'''
|-
| {{flagicon|AUS}} [[ジャック・クロフォード]] ||rowspan=3| 4
|-
| {{flagicon|AUS}} [[ケン・ローズウォール]]
|-
| {{flagicon|USA}} [[アンドレ・アガシ]] 
|}

== 優勝者一覧 ==
* [[全豪オープン男子シングルス優勝者一覧]]
* [[全豪オープン女子シングルス優勝者一覧]]
* [[全豪オープン男子ダブルス優勝者一覧]]
* [[全豪オープン女子ダブルス優勝者一覧]]
* [[全豪オープン混合ダブルス優勝者一覧]]
* [[全豪オープン (車いすテニス)]]

== 優勝賞金（男女シングルス） ==
{| class="wikitable" style="text-align: center; font-size: 95%"
|-
!大会
!金額（男子）
!金額（女子）
|-
|style="text-align:left"|[[1989年]]大会||style=text-align:right|14万0000[[AUD]]||style=text-align:right|13万5000[[AUD]]
|-
|style="text-align:left"|[[1990年]]大会||style=text-align:right|20万0000[[AUD]]||style=text-align:right|19万0000[[AUD]]
|-
|style="text-align:left"|[[1991年]]大会||colspan="2"|24万0000[[AUD]]
|-
|style="text-align:left"|[[1992年]]大会||colspan="2"|27万0000[[AUD]]
|-
|style="text-align:left"|[[1993年]]大会||colspan="2"|41万0000[[AUD]]
|-
|style="text-align:left"|[[1994年]]大会||colspan="2"|46万0000[[AUD]]
|-
|style="text-align:left"|[[1995年]]大会||colspan="2"|36万0000[[AUD]]
|-
|style="text-align:left"|[[1996年]]大会||style=text-align:right|41万5900[[AUD]]||style=text-align:right|38万0000[[AUD]]
|-
|style="text-align:left"|[[1997年]]大会||style=text-align:right|58万5000[[AUD]]||style=text-align:right|54万2000[[AUD]]
|-
|style="text-align:left"|[[1998年]]大会||style=text-align:right|61万5000[[AUD]]||style=text-align:right|57万2000[[AUD]]
|-
|style="text-align:left"|[[1999年]]大会||style=text-align:right|72万2000[[AUD]]||style=text-align:right|67万9000[[AUD]]
|-
|style="text-align:left"|[[2000年]]大会||style=text-align:right|75万5000[[AUD]]||style=text-align:right|71万7000[[AUD]]
|-
|style="text-align:left"|[[2001年]]大会||colspan="2"|83万0500[[AUD]]
|-
|style="text-align:left"|[[2002年]]大会||colspan="2"|100万0000[[AUD]]
|-
|style="text-align:left"|[[2003年]]大会||colspan="2"|112万7850[[AUD]]
|-
|style="text-align:left"|[[2004年]]大会||colspan="2"|120万0000[[AUD]]
|-
|style="text-align:left"|[[2005年]]大会||colspan="2"|120万6620[[AUD]]
|-
|style="text-align:left"|[[2006年]]大会||colspan="2"|122万0000[[AUD]]
|-
|style="text-align:left"|[[2007年]]大会||colspan="2"|128万1000[[AUD]]
|-
|style="text-align:left"|[[2008年]]大会||colspan="2"|137万0000[[AUD]]
|-
|style="text-align:left"|[[2009年]]大会||colspan="2"|200万0000[[AUD]]
|-
|style="text-align:left"|[[2010年]]大会||colspan="2"|210万0000[[AUD]]
|-
|style="text-align:left"|[[2011年]]大会||colspan="2"|220万0000[[AUD]]
|-
|style="text-align:left"|[[2012年]]大会||colspan="2"|230万0000[[AUD]]
|-
|style="text-align:left"|[[2013年]]大会||colspan="2"|243万0000[[AUD]]
|-
|style="text-align:left"|[[2014年]]大会||colspan="2"|265万0000[[AUD]]
|-
|style="text-align:left"|[[2015年]]大会||colspan="2"|300万0000[[AUD]]
|-
|style="text-align:left"|[[2016年]]大会||colspan="2"|340万0000[[AUD]]
|-
|style="text-align:left"|[[2017年]]大会||colspan="2"|370万0000[[AUD]]
|-
|style="text-align:left"|[[2018年]]大会||colspan="2"|400万0000[[AUD]]
|-
|style="text-align:left"|[[2019年]]大会||colspan="2"|410万0000[[AUD]]
|-
|style="text-align:left"|[[2020年]]大会||colspan="2"|412万0000[[AUD]]
|-
|}

== 脚注 ==
{{脚注ヘルプ}}
=== 注釈 ===
{{Reflist|group="注"}}

=== 出典 ===
{{Reflist}}

== 外部リンク ==
{{Commonscat|Australian Open (tennis)}}
* [https://ausopen.com/ 全豪オープン公式サイト]

{{全豪オープン}}
{{テニスグランドスラム大会優勝者一覧}}
{{プロテニス競技大会}}
{{authority control}}
{{デフォルトソート:せんこうおふん}}
[[Category:全豪オープン|*]]
[[Category:1905年開始のイベント]]</text>
      <sha1>2ej15rso8qtxi5u5almf53mqk3pbl1e</sha1>
    </revision>
  </page>
  