<page>
    <title>ミゾヒダニナ属</title>
    <ns>0</ns>
    <id>3062081</id>
    <revision>
      <id>93971564</id>
      <parentid>93971516</parentid>
      <timestamp>2023-02-21T11:46:19Z</timestamp>
      <contributor>
        <username>Mzaki</username>
        <id>61977</id>
      </contributor>
      <comment>移動後の編集</comment>
      <model>wikitext</model>
      <format>text/x-wiki</format>
      <text bytes="5479" xml:space="preserve">{{生物分類表
|色 = 動物界
|名称=ミゾヒダニナ属
|画像 = [[File:Oncomelania hupensis.jpg|250px]]
|画像キャプション =[[ヒューペミゾヒダニナ]]（属の[[タイプ種]]）
|界=[[動物]]界 {{sname||Animalia}}
|門=[[軟体動物]]門 {{sname||Mollusca}}
|綱=[[腹足綱]] {{sname||Gastropoda}}
|亜綱=[[新生腹足類|新生腹足亜綱]] {{sname||Caenogastropoda}}
|上目= {{sname||}}
|目= タマキビ型目{{sname||Littorinimorpha|}}
|亜目= {{sname||}}
|上科=[[クビキレガイ上科]]{{sname||Truncatelloidea}}
|科=[[イツマデガイ科]] {{sname||Pomatiopsidae}}
|属=ミゾヒダニナ属 {{snamei||Oncomelania}}
|学名={{snamei|Oncomelania}} &lt;br /&gt;[[:en:Vinzenz Maria Gredler|Gredler]], 1881&lt;ref name="Gredler, 1881"/&gt;
}}
'''ミゾヒダニナ属'''（みぞひだになぞく、溝襞蜷属）は、[[イツマデガイ科]]に分類される[[巻貝]]の[[属 (分類学)|属]]。[[タイプ種]]は[[ヒューペミゾヒダニナ]] {{snamei||Oncomelania hupensis}} Gredler, 1881（[[単型]]によるタイプ種）。 

[[日本]]、[[台湾]]、[[中華人民共和国|中国]]、[[フィリピン]]、[[インドネシア]]などの[[淡水]]域に棲息する。本属に分類される[[種 (分類学)|種]]には[[日本住血吸虫]]の[[中間宿主]]が含まれている。

==種==
[[File:Oncomelania minima.png|thumb|[[ナタネミズツボ]]（日本）]]
MolluscaBase (2021)&lt;ref name="Molluscabase=740258, 2022-06-25"/&gt;によればミゾヒダニナ属 {{snamei|Oncomelania}} には以下の種が分類される。

*{{snamei||Oncomelania bogatshevi}} (Lindholm, 1932) [[短剣符|†]]&lt;br/&gt;　分布：[[シベリア]]（[[化石種]]）
*{{snamei||Oncomelania cantoni}} (Bartsch, 1925)&lt;br/&gt;　分布：[[中国]]（[[広東]]）
*{{snamei||Oncomelania conoidalis}} Annandale, 1919 †&lt;br/&gt;　分布：[[ミャンマー]]（化石種）
*{{snamei||Oncomelania elatoides}} (Martinson &amp; Popova, 1959) †&lt;br/&gt;　分布：シベリア（化石種）
*{{snamei||Oncomelania fragilis}} Annandale, 1919 †&lt;br/&gt;　分布：ミャンマー（化石種）
*{{snamei||Oncomelania hupensis}} Gredler, 1881&lt;br/&gt;　[[ヒューペミゾヒダニナ]]（以下の亜種に分けられる）　
**亜種 {{snamei||Oncomelania hupensis chiui}} (Habe &amp; Miyazaki, 1962)&lt;br/&gt;　分布：[[台湾]]
**亜種 {{snamei||Oncomelania hupensis formosana}} (Pilsbry &amp; Hirasei, 1905)&lt;br/&gt;　[[タイワンカタヤマガイ]]　分布：台湾
**亜種 {{snamei||Oncomelania hupensis hupensis}} Gredler, 1881&lt;br/&gt;　ヒューペミゾヒダニナ（名義タイプ亜種）　分布：中国
**亜種 {{snamei||Oncomelania hupensis lindoensis}} Davis &amp; Carney, 1973&lt;br/&gt;　分布：[[スラウェシ]]
**亜種 {{snamei||Oncomelania hupensis nosophora}} (G. C. Robson, 1915)&lt;br/&gt;　[[ミヤイリガイ]]（カタヤマガイ）　分布：日本
**亜種 {{snamei||Oncomelania hupensis quadrasi}} (Möllendorff, 1895)&lt;br/&gt;　分布：[[フィリピン]]
**亜種 {{snamei||Oncomelania hupensis robertsoni}} (Bartsch, 1946)&lt;br/&gt;　分布：中国（[[四川]]・[[雲南省|雲南]]）
**亜種 {{snamei||Oncomelania hupensis tangi}} (Bartsch, 1936)&lt;br/&gt;　分布：中国（[[福建]]・[[広西]]）
*{{snamei||Oncomelania lii}} (Bartsch, 1936)&lt;br/&gt;　[[ミゾヒダニナ]]　分布：中国（[[浙江]]）
*{{snamei||Oncomelania madernyi}} Zykin, 2012 †&lt;br/&gt;　分布：シベリア（化石）
*{{snamei||Oncomelania minima}} (Bartsch, 1936)&lt;br/&gt;　[[ナタネミズツボ]]　分布：日本
*{{snamei||Oncomelania moellendorffi}} (Schmacker &amp; O. Boettger, 1890)&lt;br/&gt;　分布：中国（[[安徽]]）
*{{snamei||Oncomelania occidentalis}} (Martinson &amp; Popova, 1959) †&lt;br/&gt;　分布：シベリア（化石種）
*{{snamei||Oncomelania yaoi}} Bartsch, 1939&lt;br/&gt;　分布：中国（広東）

本属に分類されたこともある[[ヨナグニカタヤマガイ]]（ヨナクニカタヤマガイ）は別属の {{snamei||Gammatricula}} Davis &amp; Y.-Y. Liu, 1990に移されて {{snamei||Gammatricula shini}} (Habe, 1961) の学名で表記される&lt;ref name="Molluscabase=1253972, 2022-06-25"/&gt;。

{|
|[[File:Oncomelania hupensis hupensis shell.png|left|thumb|150px|ヒューペミゾヒダニナの殻。]]
|[[File:Oncomelania hupensis nosophora shell.png|left|thumb|150px|[[ミヤイリガイ]]の殻。 黒いバーは 1 mm。]]
|[[File:Oncomelania hupensis nosophora shell 2.png|left|thumb|150px|ミヤイリガイの殻口側面。 黒いバーは 1 mm。]]
|}

==出典==
&lt;div class= "references-small"&gt;
{{reflist|refs=
&lt;ref name="Gredler, 1881"&gt;
{{cite journal|author=V. M. Gredler|date=1881|title=Zur Conchylien-Fauna von China. III. Stück |journal=Jahrbücher der Deutschen Malakozoologischen Gesellschaft|volume=8|pages=110-132 (p.120-121)| url=https://www.biodiversitylibrary.org/page/16287100}}
&lt;/ref&gt;
&lt;ref name="Molluscabase=1253972, 2022-06-25"&gt;
MolluscaBase eds. (2021). MolluscaBase. Gammatricula shini (Habe, 1961). Accessed at: http://www.molluscabase.org/aphia.php?p=taxdetails&amp;id=1253972 on 2022-06-25
&lt;/ref&gt;
&lt;ref name="Molluscabase=740258, 2022-06-25"&gt;
MolluscaBase eds. (2021). MolluscaBase. Oncomelania Gredler, 1881. Accessed at: http://www.molluscabase.org/aphia.php?p=taxdetails&amp;id=740258 on 2022-06-25
&lt;/ref&gt;
}}

==外部リンク==
{{Commons category|Oncomelania}}
{{Taxonbar|from=Q5225925}}

{{Animal-stub}}

{{DEFAULTSORT:みそひたになそく}}
[[Category:イツマデガイ科]]</text>
      <sha1>s0dprx41o4eqcgepaeslaxvykb9k688</sha1>
    </revision>
  </page>
  