<page>
    <title>一時停止</title>
    <ns>0</ns>
    <id>2540999</id>
    <revision>
      <id>95451935</id>
      <parentid>95451931</parentid>
      <timestamp>2023-06-01T23:04:58Z</timestamp>
      <contributor>
        <username>Vcvfou698069</username>
        <id>1862819</id>
      </contributor>
      <minor />
      <comment>/* 一時停止すべき時間 */</comment>
      <model>wikitext</model>
      <format>text/x-wiki</format>
      <text bytes="9177" xml:space="preserve">{{otheruseslist|交通法規における一時停止|一時停止の標識一般|一時停止 (道路標識)|車の停車全般|停車|録音録画再生機器のボタン|録音録画再生機器のボタン#一時停止ボタン}}
[[File:MUTCD R1-1.svg|thumb|[[アメリカ]]で用いられている「STOP」の標識]]
'''一時停止'''（いちじていし）とは、主に[[道路交通]]において、[[車両]]などが一時的に停止すること。また、[[交差点]]やその付近において[[道路標識]]等により[[車両]]などが一時的に停止すべきことを指定されていること。

== 日本における一時停止 ==
[[ファイル:Japanese Stop Marking and Sign.jpg|サムネイル|一時停止の[[日本の道路標識]]と[[日本の路面標示|路面標示]]]]
[[File:Japan road sign 330-A.svg|thumb|日本の道路標識330（2017 - 当座）]]
日本の[[道路交通法]]には、（標識・標示によらず）一時的に停止すべき場合、および[[一時停止 (道路標識)|「一時停止」の道路標識]]等に基づき一時停止する場合が定められている。（参考：[[日本の道路標識#規制標識]]）

=== 指定場所における一時停止 ===
[[車両]]および[[路面電車]]は、交通整理が行なわれていない交差点またはその手前の直近において、[[一時停止 (道路標識)|一時停止の道路標識]]（330）等により一時停止すべきことが指定されているときは、'''道路標識等による停止線の直前（停止線がない場合は、交差点の直前）で一時停止しなければならない'''&lt;ref&gt;{{Cite book|和書|author=道路交通法実務研究会編|title=図解道路交通法|edition=5訂版|date=2017-05-10|year=2017|publisher=東京法令出版}}&lt;/ref&gt;。この場合において、交差道路を通行する車両などの進行妨害をしてはならない（道路交通法第43条）。

道路の状況、交差点における道路の優先関係&lt;ref group="注釈"&gt;交差点における車両等どうしの優先関係については、[[優先道路]]の項目を参照。ただし、一時停止の標識がある交差道路は必ずしも優先道路とはならない。&lt;/ref&gt;、他の車両の通行状況の一切いかんにかかわらず、停止すべき場所で、いったん車両が完全に停止しなければならない。停止すべき場所で完全に停止することなく、最[[徐行]]で通過した場合であっても、指定場所一時不停止の違反（反則行為）となる。

また、交差点安全進行義務などとの関係から（道路交通法第36条第4項、同法第42条第1項）、完全に一旦停止した後に、交差点の左右の安全確認を行い、さらにその後、徐行して交差点に進入するものとされている（[[自動車教習所]]の指導など）。

また、ただ単に一時停止、安全確認および徐行するだけでなく、交差点や車両の状況一切いかんにかかわらず、交差道路の車両などの進行妨害をしてはならない。そのため、交通事故が起きた場合において一時停止がある側の車両は、一時停止がない側の車両に対して一般的に不利になる（[[過失|過失割合]]）&lt;ref group="注釈"&gt;例えば住宅街等の同幅道路で同一車種どうしの出会い頭事故の場合、一時停止無し側が徐行せず、一時停止側が一時停止ないし徐行していた場合には過失割合が４：６となる。これに対し、一時停止の有無にかかわらず、優先道路または広幅道路とそうでない道路との場合、過失割合が２：８から１：９と非常に不利になる。&lt;/ref&gt;。

一時停止の道路標識が交差点の手前の30メートルの単路の場所に設置されていた場合でも、当該交差点における指定場所一時停止の効力を認めた判例がある。

=== 一時停止すべき場合 ===
[[法令]]の規定もしくは[[警察官]]の命令により、または[[危険]]を防止するための'''一時停止'''。

* 他との衝突その他の危険を予防し、防止し、または危険を回避するため
* 行き違いのための待ち合わせなどのため
* 赤信号点滅や'''一時停止'''の[[道路標識]]、[[踏切]]の直前において
* 道路外との出入りにおいて[[歩道]]や[[路側帯]]を横断する場合のその直前において
* [[横断歩道]]・[[自転車横断帯]]やその手前の直前で駐停車している他の車両の側方を通過してその前方に出ようとする直前において
* 乗降中の[[路面電車]]の後方において（ただし安全地帯があるときは徐行して通過可能）
* 発進しようとする[[バス (交通機関)|乗合自動車]]や、交差点での右左折または道路外に出るためあらかじめその場所の手前で進路変更しようとしている車両が、進路変更の合図をしている場合に譲るべき場合において
* 交差点の近傍で[[緊急自動車]]等に避譲するため
*[[停車#交差点等への進入および停止の禁止|交差点などへの進入および停止の禁止]]に従うため
* 歩道を通行している[[普通自転車]]または路側帯を通行している[[軽車両]]が歩行者に対して
* [[身体障害]]者など、視聴覚障害者、老人、児童、幼児などが通行・横断中のため

=== 一時停止すべき時間 ===
道路交通法では一時停止すべき時間（秒数）に定めはない。車体が完全に静止したことを以て「一時停止」の要件を満たす。警察による指導基準では数秒の停止状態が規定されているが、いわゆる内部基準に過ぎず、（条例で定めのある場合を除き）法令上の根拠はない。

ただし、交差点へ進入するための安全確認には一定秒数が必要となるため、客観的にみて停止時間が極端に短い場合は交差点安全進行義務違反が疑われることになる。

&lt;gallery&gt;
ファイル:Japanese stop sign (1950-1960).svg|(1950 - 1960)
ファイル:Japanese stop sign (1960-1963).svg|(1960 - 1963)
ファイル:Japan road sign 330-B.svg|(1963 - 2017)
ファイル:Japan road sign 330-A.svg|（2017 - 当座、330）[[英語]]の「[[STOP]]」が追加された。
ファイル:Japan_road_sign_329-2.svg|道路状況によっては、一時停止ではなく[[優先道路|前方優先道路]]標識が設置される&lt;ref name="交通規制基準"&gt;{{ Cite | author = [[警察庁交通局]] | date = 平成29年（2017年）4月24日 | title = 交通規制基準 | url = https://www.npa.go.jp/laws/notification/koutuu/kisei/kisei20170424.pdf | page = 141-142,144-145 }}&lt;/ref&gt;
&lt;/gallery&gt;

== アメリカにおける一時停止 ==
=== 交差点 ===
[[アメリカ合衆国]]では一時停止の標識は「STOP」で交通ルールでは原則として交差点に先着した順に安全を確認したうえで通行することとされている&lt;ref name="junglecity" /&gt;。

「STOP」の標識とともに全車一時停止が必要な交差点には「ALL WAY STOP」や、「STOP 4-WAY」（十字路の場合）または「STOP 3-WAY」（三叉路の場合）があわせて標示されている&lt;ref name="junglecity"&gt;{{Cite web|url=https://www.junglecity.com/enjoy/travel-during-your-stay/15-traffic-rules-japanese-should-know/|title=日本人が迷いやすい・間違えやすいアメリカの交通ルールを15個まとめてみた|accessdate=2019-01-23|publisher=junglecity.com}}&lt;/ref&gt;。二方向のみ一時停止であれば「STOP 2-WAY」が標示されている（一時停止の標識がない方向からはそのまま通過できる）&lt;ref name="junglecity" /&gt;。
&lt;gallery&gt;
ファイル:MUTCD R1-1.svg|アメリカで用いられている「STOP」の標識
&lt;/gallery&gt;

=== 交差点以外 ===
アメリカでは[[スクールバス]]が停車した場合、スクールバスの後続車両はその間最低25フィート（約7.62メートル）離れた場所で一時停止する必要があるほか（追い越し禁止）、スクールバスの対向車両も一時停止することが義務づけられている&lt;ref name="junglecity" /&gt;&lt;ref name="guide"&gt;ブルーガイド編集部 『ブルーガイド わがまま歩き アメリカ西海岸』[[実業之日本社]]、2017年、p.322&lt;/ref&gt;。

また、アメリカでは日本とは異なり（大型車を除いて）[[踏切]]の直前において一時停止することが禁じられている&lt;ref name="junglecity" /&gt;&lt;ref name="guide" /&gt;。

==脚注==
{{脚注ヘルプ}}
=== 注釈 ===
{{Notelist}}
=== 出典 ===
&lt;references /&gt;

== 参考文献 ==
*{{Egov law|335AC0000000105|道路交通法（昭和三十五年六月二十五日法律第百五号）}}

== 関連項目 ==
*[[停車]]
*[[一時停止標識]]

{{road-stub}}
{{DEFAULTSORT:いちしていし}}
[[Category:日本の道路交通関連法規]]</text>
      <sha1>704ujdk8c403m828pwnqyejmaq9d1dt</sha1>
    </revision>
  </page>
  