<page>
    <title>鳥取県</title>
    <ns>0</ns>
    <id>415</id>
    <revision>
      <id>95577532</id>
      <parentid>95242785</parentid>
      <timestamp>2023-06-11T12:32:21Z</timestamp>
      <contributor>
        <username>そらみみ</username>
        <id>407465</id>
      </contributor>
      <comment>/* 姉妹自治体･提携自治体 */ 江原特別自治道関連</comment>
      <model>wikitext</model>
      <format>text/x-wiki</format>
      <text bytes="71570" xml:space="preserve">{{pp-vandalism|small=yes}}
{{基礎情報 都道府県
| 都道府県名 = 鳥取県
| 画像 = 
{{multiple image
| border = infobox
| total_width = 270
| image_style = border:1;
| perrow = 2/2
| image1 = Tottori-Sakyu Tottori Japan.JPG
| image2 = Uradome_Coast_Sengan-Matsushima.JPG
| image3 = Misasa_onsen01bs3200.jpg
| image4 = Mt_Daisen_Full_View.jpg
}}
| 画像の説明 = &lt;table style="width:280px;margin:2px auto;border-collapse:collapse"&gt;
&lt;tr&gt;&lt;td style="width:50%"&gt;[[鳥取砂丘]]&lt;td style="width:50%"&gt;[[浦富海岸]]&lt;/tr&gt;
&lt;tr&gt;&lt;td style="width:50%"&gt;[[三朝温泉]]&lt;td style="width:50%"&gt;[[大山 (鳥取県)|大山]]&lt;/tr&gt;
&lt;/table&gt;
| 都道府県旗 = {{Flagicon|鳥取県|size=100px}}
| 都道府県旗の説明 = [[鳥取県旗]]
| 都道府県章 = [[File:Emblem of Tottori Prefecture.svg|70px|鳥取県章]]
| 都道府県章の説明 = 鳥取県章
| 区分 = 県
| コード = 31000-0
| ISO 3166-2 = JP-31
| 隣接都道府県 = {{flag|兵庫県}}&lt;br/&gt;{{flag|島根県}}&lt;br/&gt;{{flag|岡山県}}&lt;br/&gt;{{flag|広島県}}
| 木 = [[イチイ#キャラボク|ダイセンキャラボク]]
| 花 = [[二十世紀梨|二十世紀梨の花]]
| 鳥 = [[オシドリ]]
| シンボル名 = 他のシンボル
| 歌など = 県民の日：[[9月12日]]&lt;br /&gt;県の魚：[[ヒラメ]]&lt;br /&gt;県の歌：鳥取県民歌『[[わきあがる力]]』&lt;br /&gt;県のキャラクター : [[トリピー]]
| 郵便番号 = 680-8570
| 所在地 = [[鳥取市]]東町一丁目220番地&lt;br /&gt;{{Coord|format=dms|type:adm1st_region:JP-31|display=inline,title}}&lt;br /&gt;{{Maplink2|zoom=7|frame=yes|plain=no|frame-align=center|frame-width=220|frame-height=160|type=line|stroke-color=#cc0000|stroke-width=2|type2=point|marker2=town-hall|text=県庁舎位置}}&lt;br /&gt;[[ファイル:Tottori Prefectural Office02s3s4410.jpg|220px|鳥取県庁]]
| 外部リンク = {{Official website}}
| 位置画像 = [[ファイル:Map of Japan with highlight on 31 Tottori prefecture.svg|320px|鳥取県の位置]]{{基礎自治体位置図|31|000|image=Map of Tottori Prefecture Ja.svg}}
| 特記事項 =
}}
'''鳥取県'''（とっとりけん）は、[[日本]]の[[中国地方]]にある[[都道府県|県]]である。[[都道府県庁所在地|県庁所在地]]は[[鳥取市]]。

[[日本海側]]にあり&lt;ref name="プロフィール"&gt;[https://www.pref.tottori.lg.jp/dd.aspx?menuid=1412 鳥取県のプロフィール]鳥取県庁ホームページ（2020年1月24日閲覧）&lt;/ref&gt;、[[山陰地方]]の東側を占める。[[面積]]は約3,507[[平方キロメートル]]&lt;ref name="プロフィール"/&gt;と全国で7番目に小さく、[[人口]]は約55万人&lt;ref name="プロフィール"/&gt;&lt;ref group="注釈"&gt;鳥取県の最大人口は1988年の61万6371人。&lt;/ref&gt;で最も少ない。[[基礎自治体]]は4[[市]]14[[町#日本の地方制度としての町|町]]1[[村]]&lt;ref name="プロフィール"/&gt;で、市の数も最も少ない。

== 地理・地域 ==
=== 面積 ===
{{座標一覧|節=広袤（こうぼう）}}
[[国土地理院]]の全国都道府県市区町村別面積調によると、鳥取県の面積は{{自治体面積/鳥取県|鳥取県}}平方キロメートルである&lt;ref&gt;[https://www.gsi.go.jp/KOKUJYOHO/MENCHO-title.htm 全国都道府県市区町村別面積調] 国土地理院 2013年11月28日閲覧&lt;/ref&gt;。

[https://www.gsi.go.jp/KOKUJYOHO/CENTER/kendata/tottori_heso.pdf 国土地理院地理情報]によると、鳥取県の東西南北それぞれの端は以下の位置で東西の長さは125.41キロメートル、南北の長さは61.79キロメートルである。
{|border="1" frame="box" rules="all" cellspacing="0" cellpadding="0" style="font-size:small;text-align:center"
| ||北端&lt;br /&gt;{{ウィキ座標度分秒|35|36|52|N|134|22|12|E|type:landmark_region:JP|name=鳥取県最北端}}&lt;br /&gt;↑||重心&lt;br /&gt;{{ウィキ座標度分秒|35|21|49|N|133|50|56|E|type:landmark_region:JP|name=鳥取県重心}}
|-
|西端&lt;br /&gt;{{ウィキ座標度分秒|35|4|13|N|133|8|9|E|type:landmark_region:JP|name=鳥取県最西端}}←||中心点&lt;br /&gt;{{ウィキ座標度分秒|35|20|9.5|N|133|49|32|E|type:landmark_region:JP|name=鳥取県中心点}}||東端&lt;br /&gt;→{{ウィキ座標度分秒|35|16|40|N|134|30|55|E|type:landmark_region:JP|name=鳥取県最東端}}
|-
| ||↓&lt;br /&gt;南端&lt;br /&gt;{{ウィキ座標度分秒|35|3|27|N|133|16|9|E|type:landmark_region:JP|name=鳥取県最南端}}||
|}

=== 地形 ===
; 平野・盆地・高原
* [[鳥取平野]]
* [[倉吉平野]]
* [[米子平野]]
; 山地
[[ファイル:Daisen highest peak.jpg|thumb|大山]]
[[ファイル:湖山池.jpg|thumb|湖山池]]
* [[中国山地]]：[[大山 (鳥取県)|大山]]、[[那岐山]]、[[氷ノ山]]（[[兵庫県]][[県境]]）
; 河川
* [[千代川]]
* [[天神川]]
* [[日野川]]
; 湖沼
* [[湖山池]]
* [[東郷池]]
* [[中海]]
; 海
* [[日本海]]：[[美保湾]] - [[鳥取県の島の一覧]]
; 半島・岬
* [[弓ヶ浜半島]]（夜見ヶ浜半島）

=== 自然公園 ===
* [[国立公園]]
** [[大山隠岐国立公園]]
** [[山陰海岸国立公園]]
* [[国定公園]]
** [[氷ノ山後山那岐山国定公園]]
** [[比婆道後帝釈国定公園]]
* [[都道府県立自然公園|県立自然公園]]
** [[三朝東郷湖県立自然公園]]
** [[奥日野県立自然公園]]
** [[西因幡県立自然公園]]

=== 気候 ===
県内ほぼ全域が[[日本海側気候]]で、全域が[[豪雪地帯対策特別措置法]]に基づく[[豪雪地帯]]に指定されている。（県内全域の豪雪地帯は国内最西端。ただし、特別豪雪地帯は指定されていない。）

春と秋は好天の日が多く、夏は南風による[[フェーン現象]]で[[猛暑#猛暑日|猛暑日]]となることもあるが、平野部でも[[熱帯夜]]は少ない。

冬は曇りや雨、雪の日が多いが、平野部の1月平均気温は4[[セルシウス度|℃]]台と[[東京]]郊外や[[愛知県]][[名古屋市]]、[[京都市]]と同じくらいであり、冷え込みは厳しくない。[[米子市]]などの西部沿岸部は平年の最深積雪は20[[センチメートル]]程度と比較的雪は少ないが、東へ行くほど降雪/積雪量は多くなり、鳥取市では中心部でも平年で40センチメートル以上の最深積雪を観測する。東部では、[[日本海寒帯気団収束帯|JPCZ（日本海寒帯気団収束帯）]]の影響を受けやすい鳥取市や[[岩美町]]などの沿岸部のほうが[[智頭町]]などの内陸部よりも降雪量が多くなることがある。
特に[[大山 (鳥取県)|大山]]周辺の内陸山地は[[山陰]]一の豪雪地帯となっており、冷え込みも厳しく[[氷点下|&amp;minus;]]15°C以下にまで下がることもある。
{|class="wikitable" style="font-size:smaller;text-align:right;white-space:nowrap"
|+鳥取県内各地の平年値（統計期間：1981年 - 2010年(湖山は2003年以降)、出典：[https://www.data.jma.go.jp/obd/stats/etrn/index.php?prec_no=&amp;block_no=&amp;year=&amp;month=&amp;day=&amp;view= 気象庁・過去の気象データ検索]）
!rowspan="2" colspan="2"|平年値&lt;br /&gt;（月単位）
!colspan="8"|沿岸部
!colspan="2"|内陸部
|-
![[岩美町]]&lt;br /&gt;岩井!![[鳥取市|鳥取]]
![[鳥取市]]&lt;br /&gt;[[鳥取空港|湖山]]!![[鳥取市]]&lt;br /&gt;[[青谷町|青谷]]
![[倉吉市|倉吉]]!![[大山町]]&lt;br /&gt;塩津
![[米子市|米子]]!![[境港市|境港]]
![[智頭町|智頭]]!![[日南町]]&lt;br /&gt;茶屋
|-
!rowspan="2"|平均&lt;br /&gt;[[気温]]&lt;br /&gt;([[セルシウス度|°C]])
!最暖月
|25.5&lt;br /&gt;（8月）||27.0&lt;br /&gt;（8月）
|26.8&lt;br /&gt;（8月）||25.9&lt;br /&gt;（8月）
|26.0&lt;br /&gt;（8月）||26.0&lt;br /&gt;（8月）
|26.9&lt;br /&gt;（8月）||27.0&lt;br /&gt;（8月）
|25.1&lt;br /&gt;（8月）||23.1&lt;br /&gt;（8月）
|-
!最寒月
|3.5&lt;br /&gt;（1月）||4.0&lt;br /&gt;（1月）
|4.5&lt;br /&gt;（1月）||4.3&lt;br /&gt;（1月）
|4.2&lt;br /&gt;（1月）||4.7&lt;br /&gt;（2月）
|4.4&lt;br /&gt;（1月）||4.6&lt;br /&gt;（1月）
|1.6&lt;br /&gt;（1月）||&amp;minus;0.3&lt;br /&gt;（1月）
|-
!rowspan="2"|[[降水量]]&lt;br /&gt;([[ミリメートル|mm]])
!最多月
|244.2&lt;br /&gt;（9月）||204.0&lt;br /&gt;（9月）
|192.9&lt;br /&gt;（7月）||216.7&lt;br /&gt;（9月）
|217.9&lt;br /&gt;（9月）||226.2&lt;br /&gt;（9月）
|240.1&lt;br /&gt;（7月）||232.5&lt;br /&gt;（7月）
|229.9&lt;br /&gt;（9月）||259.9&lt;br /&gt;（7月）
|-
!最少月
|117.7&lt;br /&gt;（4月）||108.6&lt;br /&gt;（4月）
|80.1&lt;br /&gt;（4月）||104.9&lt;br /&gt;（4月）
|100.7&lt;br /&gt;（4月）||102.3&lt;br /&gt;（4月）
|104.9&lt;br /&gt;（4月）||110.6&lt;br /&gt;（4月）
|123.1&lt;br /&gt;（11月）||118.8&lt;br /&gt;（4月）
|}

=== 地域区分 ===
県域は、かつての[[因幡国]]、[[伯耆国]]に相当し、4市・5郡・14町・1村がある（町は全て「ちょう」、村は「そん」と読む。）。現在は、東部・中部・西部の3つに区分するのが一般的で、県庁所在地の鳥取市を中心とする'''東部'''は旧因幡国、[[倉吉市]]を中心とする'''中部'''と[[米子市]]や[[境港市]]を中心とする'''西部'''は旧伯耆国。旧因幡の東部に対して、同じ伯耆であった西部と中部を総称して'''中・西部'''と二区分にすることもある&lt;ref&gt;[http://www.pref.tottori.lg.jp/9577.htm 県内の市町村/とりネット/鳥取県公式サイト]&lt;/ref&gt;。また、全国的に行われている市町村合併による新規市制の発足において、新しい名称の市が誕生しなかった数少ない都道府県（他に[[神奈川県]]、[[大阪府]]、[[山形県]]、[[宮崎県]]）である。

{{日本の都道府県内自治体位置図|pref=鳥取県|float=right}}

==== 東部地区 ====
鳥取平野を中心とする旧因幡国の区域に相当し、[[鳥取砂丘]]や[[白兎海岸]]などの景勝地がある。県庁所在地で県唯一の[[中核市]]である鳥取市は、[[液晶]]工場などが立地する[[工業都市]]でもある。
* [[鳥取市]]
* [[岩美郡]][[岩美町]]
* [[八頭郡]][[若桜町]]・[[智頭町]]・[[八頭町]]

[[面積]]：{{formatnum:{{ #expr: {{自治体面積/鳥取県|鳥取市}}
 + {{自治体面積/鳥取県|岩美町}}
 + {{自治体面積/鳥取県|若桜町}}
 + {{自治体面積/鳥取県|智頭町}}
 + {{自治体面積/鳥取県|八頭町}}
 }}}}[[平方キロメートル|km&lt;sup&gt;2&lt;/sup&gt;]]、
[[推計人口]]：{{formatnum:{{ #expr: {{自治体人口/鳥取県|鳥取市}}
 + {{自治体人口/鳥取県|岩美町}}
 + {{自治体人口/鳥取県|若桜町}}
 + {{自治体人口/鳥取県|智頭町}}
 + {{自治体人口/鳥取県|八頭町}}
 }}}}人、
[[人口密度]]：{{formatnum:{{ #expr: ({{自治体人口/鳥取県|鳥取市}}
 + {{自治体人口/鳥取県|岩美町}}
 + {{自治体人口/鳥取県|若桜町}}
 + {{自治体人口/鳥取県|智頭町}}
 + {{自治体人口/鳥取県|八頭町}}) /
 ({{自治体面積/鳥取県|鳥取市}}
 + {{自治体面積/鳥取県|岩美町}}
 + {{自治体面積/鳥取県|若桜町}}
 + {{自治体面積/鳥取県|智頭町}}
 + {{自治体面積/鳥取県|八頭町}}) round 1
 }}}}人/km&lt;sup&gt;2&lt;/sup&gt;

==== 中部地区 ====
旧伯耆国の東部、倉吉平野を中心とする区域。[[白壁土蔵群]]で知られる[[倉吉市]]を中心とし、[[三朝温泉]]、[[はわい温泉]]、[[東郷温泉]]といった[[温泉地]]も多い。
* [[倉吉市]]
* [[東伯郡]][[三朝町]]・[[湯梨浜町]]・[[琴浦町]]・[[北栄町]]

[[面積]]：{{formatnum:{{ #expr: {{自治体面積/鳥取県|倉吉市}}
 + {{自治体面積/鳥取県|三朝町}}
 + {{自治体面積/鳥取県|湯梨浜町}}
 + {{自治体面積/鳥取県|琴浦町}}
 + {{自治体面積/鳥取県|北栄町}}
 }}}}km&lt;sup&gt;2&lt;/sup&gt;、
[[推計人口]]：{{formatnum:{{ #expr: {{自治体人口/鳥取県|倉吉市}}
 + {{自治体人口/鳥取県|三朝町}}
 + {{自治体人口/鳥取県|湯梨浜町}}
 + {{自治体人口/鳥取県|琴浦町}}
 + {{自治体人口/鳥取県|北栄町}}
 }}}}人、
[[人口密度]]：{{formatnum:{{ #expr: ({{自治体人口/鳥取県|倉吉市}}
 + {{自治体人口/鳥取県|三朝町}}
 + {{自治体人口/鳥取県|湯梨浜町}}
 + {{自治体人口/鳥取県|琴浦町}}
 + {{自治体人口/鳥取県|北栄町}}) /
 ({{自治体面積/鳥取県|倉吉市}}
 + {{自治体面積/鳥取県|三朝町}}
 + {{自治体面積/鳥取県|湯梨浜町}}
 + {{自治体面積/鳥取県|琴浦町}}
 + {{自治体面積/鳥取県|北栄町}}) round 1
 }}}}人/km&lt;sup&gt;2&lt;/sup&gt;

==== 西部地区 ====
かつての伯耆国西部、米子平野や[[日野川]]流域を含む地域。中国地方[[最高峰]]で[[日本百名山]]の一つ・[[大山 (鳥取県)|大山]]（1,729m）があり、古来から西隣である[[島根県]]の旧[[出雲国]]地域との結びつきが強い。
* [[米子市]]
* [[境港市]]
* [[西伯郡]][[日吉津村]]・[[大山町]]・[[南部町 (鳥取県)|南部町]]・[[伯耆町]]
* [[日野郡]][[日南町]]・[[日野町 (鳥取県)|日野町]]・[[江府町]]
** [[大山町]]のうち、旧[[中山町 (鳥取県)|中山町]]の区域については、中部として扱われることもある。

[[面積]]：{{formatnum:{{ #expr: {{自治体面積/鳥取県|米子市}}
 + {{自治体面積/鳥取県|境港市}}
 + {{自治体面積/鳥取県|大山町}}
 + {{自治体面積/鳥取県|南部町}}
 + {{自治体面積/鳥取県|伯耆町}}
 + {{自治体面積/鳥取県|日吉津村}}
 + {{自治体面積/鳥取県|日南町}}
 + {{自治体面積/鳥取県|日野町}}
 + {{自治体面積/鳥取県|江府町}}
 }}}}km&lt;sup&gt;2&lt;/sup&gt;、
[[推計人口]]：{{formatnum:{{ #expr: {{自治体人口/鳥取県|米子市}}
 + {{自治体人口/鳥取県|境港市}}
 + {{自治体人口/鳥取県|大山町}}
 + {{自治体人口/鳥取県|南部町}}
 + {{自治体人口/鳥取県|伯耆町}}
 + {{自治体人口/鳥取県|日吉津村}}
 + {{自治体人口/鳥取県|日南町}}
 + {{自治体人口/鳥取県|日野町}}
 + {{自治体人口/鳥取県|江府町}}
 }}}}人、
[[人口密度]]：{{formatnum:{{ #expr: ({{自治体人口/鳥取県|米子市}}
 + {{自治体人口/鳥取県|境港市}}
 + {{自治体人口/鳥取県|大山町}}
 + {{自治体人口/鳥取県|南部町}}
 + {{自治体人口/鳥取県|伯耆町}}
 + {{自治体人口/鳥取県|日吉津村}}
 + {{自治体人口/鳥取県|日南町}}
 + {{自治体人口/鳥取県|日野町}}
 + {{自治体人口/鳥取県|江府町}})
 / ({{自治体面積/鳥取県|米子市}}
 + {{自治体面積/鳥取県|境港市}}
 + {{自治体面積/鳥取県|大山町}}
 + {{自治体面積/鳥取県|南部町}}
 + {{自治体面積/鳥取県|伯耆町}}
 + {{自治体面積/鳥取県|日吉津村}}
 + {{自治体面積/鳥取県|日南町}}
 + {{自治体面積/鳥取県|日野町}}
 + {{自治体面積/鳥取県|江府町}}) round 1
 }}}}人/km&lt;sup&gt;2&lt;/sup&gt;

==== 気象庁による予報区分 ====
[[府県予報区]]は「鳥取県」。[[一次予報区分]]は2区分、「[[市町村等をまとめた地域]]」は5区分。[[二次予報区分]]は鳥取市以外は市町村単位で、鳥取市のみ北部・南部の2つに分かれている。
*東部
**鳥取地域 - [[鳥取市]]北部（八頭地域以外の地域）、[[岩美町]]
**八頭地域 - 鳥取市南部（旧[[河原町 (鳥取県)|河原町]]・[[用瀬町]]・[[佐治村]]の地域）、[[八頭町]]、[[若桜町]]、[[智頭町]]
*中・西部
**倉吉地域 - [[倉吉市]]、[[湯梨浜町]]、[[北栄町]]、[[三朝町]]、[[琴浦町]]
**米子地域 - [[米子市]]、[[境港市]]、[[日吉津村]]、[[大山町]]、[[南部町 (鳥取県)|南部町]]、[[伯耆町]]
**日野地域 - [[日野町 (鳥取県)|日野町]]、[[日南町]]、[[江府町]]

== 歴史 ==
=== 県名の起源にまつわる説話 ===
「鳥取」の語は、『[[古事記]]』『[[日本書紀]]』の[[垂仁天皇]]に「鳥取造（ととりのみやつこ）」や「[[鳥取部]]（ととりべ）」が見える。

『古事記』には、[[ヤマト政権|大和朝廷]]が諸国に鳥を捕らえさせ、これを税として納めるように命じていたという一節があり、当時、沼や沢の多い[[湿地帯]]であった鳥取平野で水辺に集まる鳥などを捕らえて暮らしていた狩猟民族が、[[大和国]]（現・[[奈良県]]）に政権ができてからその支配体系に組み込まれ、「鳥取部」として従属するようになり、そこからこの地が「鳥取」と呼ばれるようになったとされる&lt;ref&gt;[http://www.pref.tottori.lg.jp/item/26128.htm 民話・神話]鳥取県庁&lt;/ref&gt;。

『日本書紀』垂仁天皇二十三年九月から十一月の条にかけて「鳥取」の起源説話が見える。[[誉津別命|誉津別王子]]（ほむつわけのみこ）が成人しても言葉が喋れないことを[[天皇]]が憂いていた時、大空を[[ハクチョウ|白鳥]]が飛んでいるのを見つけ「是何物ぞ」と発した。天皇、喜びて、その鳥の捕獲を命じた。[[天湯河板挙]]（あまのゆかわたな）が鳥を追い続け各地を巡り、ついに[[出雲]]の地（現在の島根県[[安来市|安来地方]]だという説が有力）で捕獲に成功した。この功績から「鳥取造」の称号（[[姓]]＝かばね）を拝命した。『古事記』にも同類の[[説話]]が見えるが、結末が違っている。

『[[和名類聚抄]]』の因幡国[[邑美郡|邑美（おうみ）郡]]の五郷の一つに鳥取がある。この郷名は、上述の垂仁天皇の王子である本牟智和気御子（ほむちわけみこ）のために設置された鳥取部に由来する。この辺り一帯が[[沼地]]で、全国の白鳥伝説との関連が取り上げられている。文書のうえでは、[[天慶]]3年（[[940年]]）の因幡国[[高草郡]][[東大寺]]領高庭[[荘園 (日本)|庄]]坪付注進状（東南院文書）に「主張鳥取高俊」（[[郡司]]と推定）の[[署名]]が初見である&lt;ref&gt;内藤正中他『鳥取県の歴史』[[山川出版社]]（2003年）&lt;/ref&gt;。

[[山陰道]]：[[因幡国]]・[[伯耆国]]

=== 古代 ===
大山裾野丘陵から[[後期旧石器時代]]の[[黒曜石]]製と[[安山岩]]製の[[ナイフ形石器]]や[[石器|削器]]、彫器・掻器が見つかっている。今から約2万3千年前以降のものと推測される。また、旧石器時代終わり頃の黒曜石製[[細石刃]]と呼ばれる石器が発見されている。このように遺物は少数ながら発見されているが、県内からは人が生活した遺跡はまだ発見されていない。

=== 室町・戦国時代 ===
[[山名氏]]の領国であったが、[[戦国時代 (日本)|戦国時代]]末期には[[毛利輝元]]と[[織田信長]]の係争地となり、信長配下の[[豊臣秀吉|羽柴秀吉]]が[[鳥取城の戦い|鳥取城を攻略]]。配下の[[宮部継潤]]が城代を経て正式に鳥取城主となる。[[伯耆国]]においては羽柴・毛利氏の和睦により、東部は羽柴氏傘下となった[[南条元続]]が、西部は毛利方の[[吉川氏]]が所領を安堵された。

=== 江戸時代 ===
因幡国では[[関ヶ原の戦い]]で敗れた西軍方であった[[宮部長房|宮部長熈]]、[[垣屋恒総]]、[[木下重堅]]が[[改易]]され、代わって[[亀井茲矩]]、[[池田長吉]]、[[山崎家盛]]の3大名が統治した。関ヶ原の戦い以前から[[鹿野城]]主であった[[亀井氏]]に関しては加増、それ以外の大名は転封された。

伯耆国においても[[吉川広家]]([[吉川元春]]の三男)、[[南条元忠]](元続の子)が西軍方として改易・転封処分となり、[[中村一忠|中村忠一]]が入部した。[[慶長]]14年（[[1609年]]）に中村忠一が急死すると、その翌年には[[加藤貞泰]]、[[市橋長勝]]、[[関一政]]の3大名に分割された。この時、[[河村郡]]･[[久米郡 (鳥取県)|久米郡]]は[[江戸幕府]][[天領]]（直轄領）となり、[[山田直時]]･[[伊丹康勝]]が[[代官]]として派遣された。また、慶長19年（[[1614年]]）には[[里見忠義]]が[[倉吉藩|倉吉]]に[[流刑|配流]]され、久米郡の一部4,000[[石 (単位)|石]]が与えられた。

その後、[[元和 (日本)|元和]]4年（[[1618年]]）、[[池田光政]]が鳥取城に入部し、因伯2国からなる[[鳥取藩]]が成立した。このほか、[[鳥取藩#鹿奴藩|鹿奴藩]]･[[鳥取藩#若桜藩|若桜藩]]の2つの新田藩があった。

伯耆国[[汗入郡]]の[[大山寺 (鳥取県大山町)|大山寺]]は僧・[[豪円]]の活躍によって慶長15年（[[1610年]]）、[[徳川秀忠]]より[[寺社領|寺領]]3,000石が認められた。この大山寺領は西伯耆一帯に散在し、18ヵ村が大山寺本坊西楽院の管掌下に置かれた。大山寺は鳥取藩士とは別の[[大山侍]]と呼ばれる[[武士]]を登用し、寺領支配に携わらせた。

=== 近現代 ===
* [[1871年]]（[[明治4年]]）[[7月14日 (旧暦)]] - [[廃藩置県]]により旧[[因幡国]]の8郡（[[岩井郡]]・[[邑美郡]]・[[法美郡]]・[[八上郡 (鳥取県)|八上郡]]・[[八東郡]]・[[智頭郡]]・[[高草郡]]・[[気多郡 (鳥取県)|気多郡]]）、旧[[伯耆国]]の6郡（[[河村郡]]・[[久米郡 (鳥取県)|久米郡]]・[[八橋郡]]・[[汗入郡]]・[[会見郡]]・[[日野郡]]）、旧[[播磨国]]の3郡（[[神東郡]]・[[神西郡]]・[[印南郡]]）の一部が鳥取県となった。
** [[11月15日 (旧暦)]] - 旧播磨国の領域が[[姫路県]]に編入される。
** [[12月27日 (旧暦)]] - [[島根県]]より旧[[隠岐国]]が編入される。
* [[1872年]]（[[明治5年]]） - 1月、県下を112の区に分け、[[戸長]]・副戸長を任命する。7月、郵便取扱所を設置する。
* [[1873年]]（[[明治]]6年） - 6月、会見郡に[[徴兵制]]反対の[[一揆]]勃発する。12月、大区・小区制施行される。
* [[1874年]]（明治7年） - 8月、[[地租改正]]に着手する。
* [[1876年]]（明治9年）[[8月21日]] - 鳥取県が島根県に併合、鳥取に支庁を設置する。併合は、島根[[県令]]代理の布告で突然行われたため、以後、鳥取県分離運動が盛んになる&lt;ref&gt;{{Cite web |date= 2018-08-22|url= https://www.yomiuri.co.jp/fukayomi/ichiran/20180821-OYT8T50044.html?page_no=3&amp;from=yartcl_page|title= “受難”再び…地図から消された「あの2県」 |publisher= 『[[読売新聞]]』|accessdate=2018-08-25}}{{リンク切れ|date=2023年3月}}&lt;/ref&gt;。
* [[1881年]]（明治14年）[[9月12日]] - 島根県のうち、旧因幡国の8郡、旧伯耆国の6郡が鳥取県として分立・再置される。
* [[1889年]]（明治22年）
* [[10月1日]] - 市制施行により、[[邑美郡]]の一部から[[鳥取市]]が発足。
* [[10月1日]] - [[日吉津村]]が発足（県内で唯一発足から現在に至るまで合併を経験していない市町村）。
* [[1896年]]（明治29年）[[4月1日]] - 岩井郡・邑美郡・法美郡が合併し[[岩美郡]]、八上郡・八東郡・智頭郡が合併し[[八頭郡]]、気多郡・高草郡が合併し[[気高郡]]、河村郡・久米郡・八橋郡が合併して[[東伯郡]]、汗入郡・会見郡が合併し[[西伯郡]]が発足。
* [[1909年]]（明治42年）[[4月1日]] - 八頭郡若桜村ほか2村が新設合併して町制施行。八頭郡[[若桜町]]が発足。
* [[1914年]]（[[大正]]3年）[[6月1日]] - 八頭郡智頭村が町制施行。八頭郡[[智頭町]]が発足。
* [[1927年]]（[[昭和]]2年）[[4月1日]] - 西伯郡米子町が鳥取県下で2番目に市制施行。[[米子市]]が発足。
* [[1953年]]（昭和28年）
** [[6月1日]] - 日野郡江尾村ほか2村が対等合併。日野郡[[江府町]]となる。
** [[10月1日]] - 東伯郡倉吉町ほか1町7村が新設合併し、鳥取県下で3番目に市制施行。[[倉吉市]]が発足。
** [[11月1日]] - 三朝村ほか4村が新設合併し、町制施行。東伯郡[[三朝町]]が発足。
* [[1954年]]（昭和29年）[[7月1日]] - 岩美郡浦富町ほか1町7村が新設合併し、岩美郡[[岩美町]]が発足。
* [[1955年]]（昭和30年）[[9月1日]] - 西伯郡所子村、高麗村（今津を除く）が新設合併し、町制施行。西伯郡[[大山町]]となる。
* [[1956年]]（昭和31年）[[4月1日]] - 西伯郡境港町が鳥取県下で4番目に市制施行。[[境港市]]が発足。
* [[1959年]]（昭和34年）
** [[4月1日]] - 日野郡伯南町ほか4村が対等合併し、日野郡[[日南町]]が発足。
** [[5月1日]] - 日野郡根雨町と黒坂町が対等合併し、日野郡[[日野町 (鳥取県)|日野町]]が発足。
* [[2004年]]（[[平成]]16年）[[9月1日]] - 東伯郡[[東伯町]]、[[赤碕町]]が新設合併し、東伯郡[[琴浦町]]が発足。
* [[10月1日]] - 東伯郡[[羽合町]]、[[泊村 (鳥取県)|泊村]]、[[東郷町 (鳥取県)|東郷町]]が新設合併し、東伯郡[[湯梨浜町]]が発足。
* [[10月1日]] - 西伯郡[[西伯町]]、[[会見町]]が新設合併し、西伯郡[[南部町 (鳥取県)|南部町]]が発足。
* [[11月1日]] - 鳥取市が[[岩美郡]][[国府町 (鳥取県)|国府町]]、[[福部村]]、[[気高郡]][[気高町]]、[[鹿野町 (鳥取県)|鹿野町]]、[[青谷町]]、[[八頭郡]][[河原町 (鳥取県)|河原町]]、[[用瀬町]]、[[佐治村]]の8町村を編入。これにより、気高郡が同日消滅。
* [[2005年]]（平成17年）
** [[1月1日]] - 西伯郡[[岸本町]]、[[日野郡]][[溝口町]]が新設合併し、西伯郡[[伯耆町]]が発足。
** [[3月22日]] - 倉吉市が東伯郡[[関金町]]を編入。
** [[3月28日]] - 西伯郡旧・大山町、[[名和町]]、[[中山町 (鳥取県)|中山町]]が新設合併し、西伯郡新・大山町となる。
** [[3月31日]] - 旧・米子市、西伯郡[[淀江町]]が新設合併し、新・米子市が発足。
** [[3月31日]] - 八頭郡[[郡家町 (鳥取県)|郡家町]]、[[船岡町 (鳥取県)|船岡町]]、[[八東町]]が新設合併し、八頭郡[[八頭町]]が発足。
** [[10月1日]] - 東伯郡[[北条町 (鳥取県)|北条町]]、[[大栄町 (鳥取県)|大栄町]]が新設合併し、東伯郡[[北栄町]]が発足。
** [[10月1日]] - 鳥取市が山陰初の[[特例市]]に指定される。
* [[2011年]]（平成23年）[[1月1日]] - 年末寒波の影響で県西部で記録的な大雪となり、[[国道9号]]線の大渋滞や鉄塔が折れるなどの被害が発生。
* [[2012年]]（平成24年）[[9月8日]] - [[日本海]]に面する、鳥取を含む10府県が合同で[[海洋エネルギー資源開発促進日本海連合]]を設立&lt;ref&gt;[http://sankei.jp.msn.com/life/news/120908/trd12090812490005-n1.htm 「海底資源開発で連携 日本海沿岸の10府県」]『[[産経新聞]]』2012年9月8日{{リンク切れ|date=2017年10月}}。他の参加府県は[[秋田県]]、[[山形県]]、[[新潟県]]、[[富山県]]、[[石川県]]、[[福井県]]、[[京都府]]、[[兵庫県]]、[[島根県]]。&lt;/ref&gt;&lt;ref&gt;[http://www.kobe-np.co.jp/news/shakai/0005363224.shtml 「メタンハイドレート活用研究 10府県が会議設立」]『[[神戸新聞]]』2012年9月8日{{リンク切れ|date=2017年10月}}&lt;/ref&gt;&lt;ref&gt;[http://www.niigata-nippo.co.jp/news/pref/39824.html 「日本海の資源開発で連携、連合設立。本県など日本海側10府県」]『[[新潟日報]]』2012年9月10日&lt;/ref&gt;&lt;ref&gt;[http://www.asahi.com/eco/news/TKY201209080579.html 「メタンハイドレート、日本海でも調査を 10府県が連合」]『[[朝日新聞]]』2012年9月9日&lt;/ref&gt;。
* [[2013年]]（平成25年）[[10月8日]] - 日本で初めて[[手話]]を言語として扱う[[条例]]を可決&lt;ref&gt;[http://www.pref.tottori.lg.jp/220879.htm 鳥取県手話言語条例]&lt;/ref&gt;&lt;ref&gt;[http://www.pref.tottori.lg.jp/222957.htm 条例の新設理由]&lt;/ref&gt;&lt;ref&gt;[https://www.youtube.com/watch?v=ZO2AXmTHOn4 手話でコミュニケーション－鳥取県手話言語条例制定－]&lt;/ref&gt;&lt;ref&gt;[http://www.jfd.or.jp/2013/10/08/pid11362 鳥取県で全国初の手話言語条例が成立!]&lt;/ref&gt;&lt;ref&gt;[http://www.asahi.com/politics/update/1008/OSK201310080005.html 「手話は言語」条例、鳥取県が制定 全国初]&lt;/ref&gt;&lt;ref&gt;[http://www.nhk.or.jp/heart-net/rounan/backnumber/2014/06/0622.html 町に手話が広がった―手話言語条例の鳥取県は今―]&lt;/ref&gt;&lt;ref&gt;[http://www.fukushishimbun.co.jp/topics/463 鳥取県が初の手話言語条例　年度内制定へ検討]&lt;/ref&gt;&lt;ref&gt;[http://www.yomidr.yomiuri.co.jp/page.jsp?id=88314 全国初の手話言語条例、鳥取県HPに手話コーナー]&lt;/ref&gt;&lt;ref&gt;[http://torideaf.jp/publics/index/13/ 鳥取県手話言語条例が可決・成立しました]&lt;/ref&gt;&lt;ref&gt;[http://www.shintoku-town.jp/kurashi/fukushi/syuwajyourei 手話に関する基本条例が施行されました。]&lt;/ref&gt;。
* [[2014年]]（平成26年）[[11月5日]] - 観光キャンペーンの期間限定で「鳥取県」を「蟹取県」に改名&lt;ref&gt;「[http://j-town.net/tottori/news/localnews/194743.html 鳥取県、とうとう県名を変える]」&lt;/ref&gt;&lt;ref&gt;[http://www.tottori-guide.jp/wel-kani/ 鳥取県ウェルカニ]&lt;/ref&gt;。

== 人口 ==
全国の都道府県で最も人口が少ない。また、全国どの[[政令指定都市]]と比較しても人口が少なく、政令指定都市以外で最大の[[千葉県]][[船橋市]]や[[埼玉県]][[川口市]]、[[鹿児島県]]の[[都道府県庁所在地|県庁所在地]][[鹿児島市]]、[[東京都]]唯一の[[中核市]]である[[八王子市]]よりも少ない。2021年3月には、県の人口が戦後初めて55万人を割り込んだ&lt;ref&gt;{{Cite web|url=https://www.kyoto-np.co.jp/articles/-/533014|title=鳥取県人口、戦後初５５万人割れ|accessdate=2021年9月30日|publisher=}}&lt;/ref&gt;。

県外からの移住者は年間2,000人程度で、休暇（バケーション）を楽しみやすい土地で仕事（ワーク）をしてもらう「ワーケーション」を掲げるなどして移住者誘致を図っている&lt;ref name="日経20191219"&gt;『[[日本経済新聞]]』朝刊2019年12月19日33面【山陰経済特集】きらめく山陰 人を呼ぶ：「星空舞」や薬草 食に新顔／「仕事しつつ休暇」移住加速へ試す&lt;/ref&gt;。

ただし、面積も小さいことから[[人口密度]]で見ると168.5人/平方キロメートルと37位で、鹿児島県・[[長野県]]のそれと近い&lt;ref&gt;[http://www.pref.tottori.lg.jp/dd.aspx?menuid=154080#tag02 平成22年版100の指標からみた鳥取県]&lt;/ref&gt;。
[[ファイル:Growth rate map of municipalities of Tottori prefecture, Japan.svg|thumb|300px|鳥取県人口増減率分布図（2005年度と2010年度国勢調査から算出）
{{Multicol}}
'''増加'''
{{legend|#44AA00|7.5 - 9.99 %}}
{{Multicol-break}}
'''減少'''
{{Legend|#FFAAAA|0.0 - 2.5 %}}
{{Legend|#FF5555|2.5 - 5.0 %}}
{{Legend|#FF0000|5.0 - 7.5 %}}
{{Legend|#AA0000|7.5 - 10.0 %}}
{{Legend|#550000|10.0 % 以上}}
{{Multicol-end}}]]
{{人口統計|code=31000|name=鳥取県|image=Demography31000.svg}}

== 政治 ==
=== 県政 ===
{{Main|鳥取県知事一覧|鳥取県庁|鳥取県議会}}
* [[都道府県知事|知事]]:[[平井伸治]]（ひらい しんじ、4期目）
鳥取県の[[行政]]機関は、鳥取県庁のほか、地方機関として総合事務所等が置かれている&lt;ref&gt;{{Cite web |date= |url=https://www.pref.tottori.lg.jp/soshiki/ |title=県の組織と仕事 |publisher=鳥取県庁 |accessdate=2019-01-02}}&lt;/ref&gt;。なお、[[鳥取市]]・[[岩美町]]・[[若桜町]]・[[智頭町]]・[[八頭町]]については本庁が担当する。伯耆町（旧[[溝口町]]）は[[2005年]]（平成17年）[[4月1日]]に日野総合事務所から西部総合事務所へ、鳥取市（[[河原町 (鳥取県)|河原町]]・[[用瀬町]]・[[佐治村|佐治町]]）は[[2007年]]（平成19年）[[4月1日]]に八頭総合事務所から東部総合事務所へ、それぞれ移管された。[[2013年]]（平成25年）4月1日に東部・八頭の各総合事務所が本庁に集約、日野総合事務所が西部総合事務所日野振興センターとなった。[[2014年]]（平成26年）4月1日に県税部門の一部の業務が特定の県税事務所に集約された&lt;ref&gt;{{Cite web |date= |url=https://www.pref.tottori.lg.jp/225580.htm |title=平成26年4月1日から県税の一部業務が集約化されます |publisher=鳥取県総務部税務課 |accessdate=2019-01-02}}&lt;/ref&gt;。[[2018年]]（平成30年）4月1日の鳥取市の中核市移行に伴い、東部福祉保健事務所・東部生活環境事務所が鳥取市に移譲され、鳥取市保健所となった（管轄区域は変更なし。岩美町・若桜町・智頭町・八頭町についても、鳥取県からの事務委託により鳥取市に移譲）。

* 本庁（鳥取市）：[[鳥取市]]、[[岩美町]]、[[若桜町]]、[[智頭町]]、[[八頭町]]
** 元気づくり総本部
*** 東部振興監・東部振興課
** 総務部
*** 東部県税事務所（鳥取市）：鳥取市、岩美町、若桜町、智頭町、八頭町（ただし、[[道府県民税|県民税利子割・法人県民税]]、[[事業税|法人事業税]]、[[地方法人特別税]]、[[道府県たばこ税|県たばこ税]]については全域）
*** 中部県税事務所（倉吉市）：倉吉市、三朝町、湯梨浜町、琴浦町、北栄町（ただし、[[鉱区税]]・産業廃棄物処分場税（[[法定外目的税]]）については全域）
*** 西部県税事務所（米子市）：米子市、境港市、日吉津村、大山町、南部町、伯耆町（ただし、[[ゴルフ場利用税]]・[[軽油引取税]]については全域）
**** 日野支所（日野町）：日南町、日野町、江府町
** 農林水産部
*** 東部農林事務所（鳥取市）：鳥取市、岩美町
**** 八頭事務所（八頭町）：若桜町、智頭町、八頭町
** 県土整備部
*** 鳥取県土整備事務所（鳥取市）：鳥取市、岩美町
*** 八頭県土整備事務所（八頭町）：若桜町、智頭町、八頭町
* 中部総合事務所（倉吉市）：[[倉吉市]]、[[三朝町]]、[[湯梨浜町]]、[[琴浦町]]、[[北栄町]]
** 地域振興局
** 福祉保健局（倉吉保健所（福祉保健部門））
** 生活環境局（倉吉保健所（生活環境部門））
** 農林局
** 県土整備局
* 西部総合事務所（米子市）：[[米子市]]、[[境港市]]、[[日吉津村]]、[[大山町]]、[[南部町 (鳥取県)|南部町]]、[[伯耆町]]、[[日南町]]、[[日野町 (鳥取県)|日野町]]、[[江府町]]
** 地域振興局：米子市、境港市、日吉津村、大山町、南部町、伯耆町
** 福祉保健局（米子保健所（福祉保健部門））
** 生活環境局（米子保健所（生活環境部門））
** 農林局：米子市、境港市、日吉津村、大山町、南部町、伯耆町
** 米子県土整備局：米子市、境港市、日吉津村、大山町、南部町、伯耆町
** 日野振興センター（日野町）：日南町、日野町、江府町
*** 日野振興局
*** 日野県土整備局

=== 財政 ===
==== 平成19年度 ====
* [[財政力指数]] 0.27
**IVグループ（財政力指数0.4未満）6自治体中4位

==== 平成18年度 ====
* 標準財政規模 1881億5700万円
* 一般会計歳入 3763億円
* 一般会計歳出 3695億円
* 財政力指数 0.26
** IVグループ（財政力指数0.4未満）10自治体中8位
* 経常収支比率 92.8％（都道府県平均 92.6）
* 実質収支比率 2.71％
* 人口100,000人当たり職員数 1,792.17人（都道府県平均 1,173.11人）
* [[ラスパイレス指数]] 97.3（都道府県平均 99.6）
* 人口1人あたり人件費・物件費等決算額　18万5089円（都道府県平均 12万4759円）
** 人口規模が大きいほうが規模のメリットが出る指標である
* 実質公債費比率 13.0％（都道府県平均 14.7％）
* 人口1人当たり地方債現在高 100万9078円（都道府県平均 62万2416円）
地方債の残高
* 普通会計分の地方債現在高 6122億円
* 上記以外の特別会計分の地方債現在高 304億円
** 特に病院事業会計分 128億4700万円
* 他に[[第三セクター]]等に債務保証残高等
** 鳥取県農業開発公社の損失補償に係る債務残高 84億9462万円

==== 平成17年度 ====
*財政力指数 0.24
**IVグループ（財政力指数0.4未満）14自治体中12位

==== 平成16年度 ====
*財政力指数 0.23
**IVグループ（財政力指数0.4未満）15自治体中13位

=== 歴代知事（公選） ===
* 初代 [[西尾愛治]]（1947年4月12日～1954年11月7日、2期）
* 2代 [[遠藤茂]]（1954年12月7日～1958年11月10日、1期）
* 3代 [[石破二朗]]（1958年12月3日～1974年2月22日、4期）
* 4代 [[平林鴻三]]（1974年3月27日～1983年3月9日、3期）
* 5代 [[西尾邑次]]（1983年4月13日～1999年4月12日、4期）
* 6代 [[片山善博]]（1999年4月13日～2007年4月12日、2期）
* 7代 [[平井伸治]]（2007年4月13日～）

=== 国政 ===
{{Main|衆議院小選挙区制選挙区一覧#鳥取県|鳥取県・島根県選挙区}}
[[衆議院]]の[[小選挙区]]が2区ある。[[参議院]]では[[鳥取県選挙区]]として全県で1区を構成していたが、2016年の[[第24回参議院議員通常選挙]]より[[島根県選挙区]]と合区され、[[鳥取県・島根県選挙区]]となり島根県とともに1区を構成する[[参議院合同選挙区|合同選挙区]]が創設された。

== 経済・産業 ==
=== 県内総生産 ===
人口が日本国内で一番少ない県であるため、県内総生産（名目GDP）も[[2008年]]4月から[[2009年]]3月までのベース（平成20年度の統計）で1兆9927億円&lt;ref&gt;[http://www.pref.tottori.lg.jp/secure/544590/100201201002b.pdf 平成20年度鳥取県県民経済計算の概要]&lt;/ref&gt;と47都道府県では最も小さく、世界の中では[[国内総生産]] (GDP) のランクが90位程度の国と同程度である&lt;ref&gt;[http://ecodb.net/ranking/imf_ngdpd.html 世界の名目GDPランキング]&lt;/ref&gt;。なお、これを一人当たりで見ると[[和歌山県]]・[[岩手県]]のそれに近い。また、一人当たり県民所得は230.4万円であり、全国平均の83.7%である。これは、[[熊本県]]・[[鹿児島県]]のそれに近い。

ちなみに、鳥取県は[[スターバックス]]が未出店である唯一の県だったが、[[2015年]][[5月23日]]に同店の鳥取県1号店が[[鳥取市]]の[[鳥取駅]]南口付近に開業した。これにより、スターバックスは47[[都道府県]]全てに店舗を構えることになった。その後、[[イオンモール鳥取北]]内にも出店している。
=== 産業別人口 ===
* [[第一次産業]] 10.9％
* [[第二次産業]] 24.8％
* [[第三次産業]] 64.3％

=== 特産品 ===
[[農作物]]では[[スイカ]]（西瓜）、[[らっきょう]]、[[ナシ#二十世紀|二十世紀梨]]など全国的に有名。[[米]]や[[野菜]]、[[果物]]などもバランスよく生産されている。砂丘らっきょう、大山[[ブロッコリー]]、こおげ花御所[[柿]]、大栄西瓜は[[地理的表示]]（GI）登録されている&lt;ref name="日経20191219"/&gt;。

海産物では[[ズワイガニ|松葉ガニ]]が名産で、「五輝星」（いつきぼし）という県認定ブランド蟹がある&lt;ref name="日経20191219"/&gt;。

=== 農業 ===
&lt;references group="グループ名" /&gt;
農業生産額の割合は野菜が全生産額の28.4%で最も多く、米が19.5%、[[ニワトリ|鶏]]（[[鶏卵]]・[[ブロイラー]]）が13.6%、[[乳牛|乳用牛]]が10.5%、果実9.4%を占めている。&lt;ref&gt;{{Cite web|url=https://www.e-stat.go.jp/stat-search/files?page=1&amp;layout=datalist&amp;toukei=00500206&amp;tstat=000001015617&amp;cycle=7&amp;year=20180&amp;month=0&amp;tclass1=000001019794&amp;tclass2=000001138686|title=平成30年生産農業所得統計|accessdate=2020年4月18日|publisher=}}&lt;/ref&gt;
{{表2列|
*二十世紀梨
* [[新甘泉]]
* [[白ねぎ]]
*スイカ
* [[芝]]
|
* [[しいたけ]]
* [[長いも]]
*らっきょう
*ブロッコリー
*ぶどう
}}
=== 漁業 ===
{{表2列|
* [[ズワイガニ|松葉ガニ]]
* [[カキ (貝)|岩ガキ]]
* [[イカ|白イカ]]
|
* [[イワシ]]
* [[カレイ]]
* [[マグロ]]
}}

=== 商業 ===
;卸・小売業
* [[サンマート (鳥取県)|サンマート]]（鳥取市）
* [[エスマート (鳥取県)|Sマート]]（鳥取市）
* [[丸合]]（米子市）
* [[東宝企業]]（倉吉市）
* [[いない]]（倉吉市）
;金融機関
* [[山陰合同銀行]]（本店は島根県の[[松江市]]だが、県の[[指定金融機関]]である。）
* [[鳥取銀行]]（県[[指定代理金融機関]]。本店・鳥取市）
* [[鳥取県信用農業協同組合連合会]]（[[指定代理金融機関]]。本店・鳥取市）
*鳥取県[[JFマリンバンク|信用漁業協同組合連合会]]（[[指定代理金融機関]]。本店・鳥取市）
* [[鳥取信用金庫]]（本店・鳥取市）
* [[倉吉信用金庫]]（本店・倉吉市）
* [[米子信用金庫]]（本店・米子市）
*他に[[みずほ銀行]]、[[中国銀行 (日本)|中国銀行]]、[[島根銀行]]、[[三井住友信託銀行]]等が県内に支店を置いている。
;県内に店舗を置く主要企業
{{Col|
* [[髙島屋]]
* [[イオン (店舗ブランド)|イオン]]
* [[マックスバリュ]]
* [[ローソン]]
* [[セブン-イレブン]]
* [[ファミリーマート]]
* [[ポプラ (コンビニエンスストア)|ポプラ]]
* [[日本マクドナルド|マクドナルド]]
* [[モスバーガー]]
* [[バーガーキング (日本)|バーガーキング]]
|
* [[天下一品]]
* [[来来亭]]
* [[物語コーポレーション|丸源ラーメン]]
* [[ホッコク|どさん子]]
* どさん子大将
* どさん娘
* [[リンガーハット]]
* [[餃子の王将]]
* [[イートアンド|大阪王将]]
* [[はなまるうどん]]
* [[丸亀製麺]]
* [[トライ・インターナショナル|麺場 田所商店]]
|
* [[かっぱ寿司]]
* [[無添くら寿司]]
* [[あきんどスシロー|スシロー]]
* [[はま寿司]]
* [[KFCコーポレーション|ケンタッキーフライドチキン]]
* [[すき家]]
* [[吉野家]]
* [[なか卯]]
* [[すかいらーく|ガスト]]
* [[すかいらーく|とんから亭]]
* [[かつや]]
|
* [[トマトアンドアソシエイツ|トマト＆オニオン]]
* [[すかいらーく|しゃぶ葉]]
* [[ココスジャパン|Coco's]]
* [[ビッグボーイ (レストラン)|ビッグボーイ]]
* [[ジョリーパスタ]]
* [[サイゼリヤ]]
* [[ジョイフル]]
* [[ピザハット]]
* [[ドミノ・ピザ]]
* [[大戸屋ホールディングス|大戸屋ごはん処]]
* [[いきなり!ステーキ]]
* [[壱番屋|CoCo壱番屋]]
* [[スパイス王国]]
* [[ミスタードーナツ]]
* [[フロレスタ (ドーナツ店)|フロレスタ]]
|
* [[モンテローザ (企業)|魚民]]
* [[モンテローザ (企業)|笑笑]]
* [[レインズインターナショナル|しゃぶしゃぶ温野菜]]
* [[レインズインターナショナル|牛角]]
* [[さかい (焼肉屋)|焼肉屋さかい]]
* [[スターバックス]]
* [[ドトールコーヒー]]
* [[タリーズコーヒー]]
* [[コメダ珈琲店]]
* [[マルハン]]
* [[サンマルクホールディングス|サンマルクカフェ、倉式珈琲店]]
|
* [[ゴディバ]]
* [[ビアード・パパ]]
* [[100満ボルト]]
* [[エディオン]]
* [[ヤマダ電機]]
* [[ケーズホールディングス|ケーズデンキ]]
* [[コーナン]]
* [[コメリ]]
* [[ナフコ (ホームセンター)|ナフコ]]
* [[ジュンテンドー]]
* [[ナンバ (ホームセンター)|ナンバ]]
|
* [[カインズ|カインズホーム]]
* [[PLANT]]
* [[大黒天物産|ラ・ムー、ディオ、ザ・大黒天]]
* [[トライアルカンパニー|トライアル]]
* [[ダイレックス (ディスカウントストア)|ダイレックス]]
* [[ドン・キホーテ (企業)|ドン・キホーテ]]
* [[ザ・ビッグ]]
* [[ニトリ]]
* [[ロフト (雑貨店)|LOFT]]
* [[良品計画|無印良品]]
* [[トイザらス]]
* [[アニメイト]]
|
* [[ツルハグループドラッグ&amp;ファーマシー西日本|ドラッグストアウェルネス]]
* [[ココカラファイン|シンヤクドー、ココカラファイン]]
* [[サンドラッグ]]
* [[ゴダイ|ゴダイドラッグ]]
* [[マツモトキヨシ]]
* [[コクミン]]
* [[コスモス薬品|ディスカウントドラッグコスモス]]
* [[ププレひまわり|スーパードラッグひまわり]]
* [[ザグザグ]]
* [[ウエルシア薬局|ウエルシア]]
}}{{clear}}

=== 工業 ===
; 県内に本社を置く主要企業
* ホームセンターいない（倉吉市）
* [[日本セラミック]]（鳥取市）
* [[吉谷機械製作所]]（鳥取市）
* [[FDK鳥取]]（岩美町）
* [[オムロン倉吉]]（倉吉市）
* [[オンキヨートレーディング]](鳥取オンキヨー)（倉吉市）
* [[寿スピリッツ]]（米子市）
* [[丸京製菓]]（米子市）
* [[宝製菓 (鳥取県)|宝製菓]]（琴浦町）
* [[ニチラス]]（米子市）
* [[百年住宅パネル工業]]（米子市）
* [[井ゲタ竹内]]（境港市）
* 日本きのこセンター（鳥取市）
* [[八幡物産]]（米子市）
* [[シャープ米子]]（米子市）
; 県内に拠点事業所を置く主要企業
* [[王子製紙]]米子工場（米子市）
* [[ニッポン高度紙工業]]米子工場（米子市）
* [[ミネベアミツミ]]米子工場（米子市）
* [[鶴見製作所]]米子工場 (米子市)
* [[サントリープロダクツ]]天然水奥大山ブナの森工場（江府町）：[[サントリー天然水]]奥大山
* [[コカ・コーラボトラーズジャパン]]大山工場（伯耆町）：[[森の水だより]]、[[い・ろ・は・す]]
* [[グリコマニュファクチャリングジャパン]]鳥取工場（南部町）

== 生活・交通 ==
=== 警察 ===
{{Main|鳥取県警察}}
鳥取県警察本部の管轄にある。[[2005年]]（平成17年）[[4月1日]]に再編が行われ、以下の9警察署が置かれている。
* [[鳥取警察署]]（鳥取市）:[[鳥取市]]（本庁・国府町・福部町地区）、[[岩美町]]
* [[郡家警察署]]（八頭町）:[[若桜町]]、[[八頭町]]
* [[智頭警察署]]（智頭町）:鳥取市（河原町・用瀬町・佐治町地区）、[[智頭町]]
* [[浜村警察署]]（鳥取市）:鳥取市（気高町・鹿野町・青谷町地区）
* [[倉吉警察署]]（倉吉市）:[[倉吉市]]、[[三朝町]]、[[湯梨浜町]]、[[北栄町]]
* [[琴浦大山警察署]]（琴浦町）:[[琴浦町]]、[[大山町]]
* [[米子警察署]]（米子市）:[[米子市]]、[[日吉津村]]、[[南部町 (鳥取県)|南部町]]
* [[境港警察署]]（境港市）:[[境港市]]
* [[黒坂警察署]]（日野町）:[[伯耆町]]、[[日南町]]、[[日野町 (鳥取県)|日野町]]、[[江府町]]

=== 交通 ===
おおむね、兵庫県境～島根県境までの海岸線に沿った旧[[山陰道]]のルートに沿って走る幹線（鉄道の[[山陰本線]]や[[国道9号]]線）が県内主要都市（もしくはその付近）を通り、鳥取・米子・倉吉の各都市近辺から中国山地・[[山陽地方|山陽]]方面へルートが分岐する構造になっている。

==== 鉄道 ====
県内一帯で普通列車の本数は米子市近郊の一部区間を除いて毎時1本以下となっており、県内における営業列車の運用は臨時列車を除きすべて当日中に終了する（=日付越えの運用は行われていない）。
（）のないものは県内のみを走る路線。
* [[西日本旅客鉄道]]
** [[山陰本線]]（[[東浜駅]]～[[米子駅]]間）
** [[伯備線]]（[[上石見駅]]～[[伯耆大山駅]]間）
** [[因美線]]（[[鳥取駅]]～[[那岐駅]]間）
** [[境線]]
* [[若桜鉄道]]
** [[若桜鉄道若桜線|若桜線]]
[[ファイル:Chizu Express-HOT7000DC.jpg|thumb|智頭急行を経由して鳥取と[[関西]]を結ぶ特急「[[スーパーはくと]]」の車両]]
* [[智頭急行]]
** [[智頭急行智頭線|智頭線]]（[[山郷駅]]～[[智頭駅]]間）
;廃止された鉄道路線
* [[日本国有鉄道]]・[[倉吉線]]
* [[日ノ丸自動車]]・[[日ノ丸自動車法勝寺電鉄線|法勝寺電鉄線]]
* [[米子電車軌道]]
* [[岩井町営軌道]]

==== バス ====
[[日ノ丸自動車]]、[[日本交通 (鳥取県)|日本交通]]の2社があり、県内の[[路線バス]]や県内各都市と県外を結ぶ[[高速バス]]を運行。
; その他の観光周遊バス・主な市町村委託バス
* 鳥取市100円循環バス[[くる梨]]
* [[ループ麒麟獅子]]（鳥取市）
* [[だんだんバス]]（米子市巡回バス）
* [[どんぐりコロコロ]]（米子市淀江町巡回バス）
* [[はまるーぷバス]]（境港市）
どんぐりコロコロは米子第一交通の運行、はまるーぷバスは共立メンテナンスの運行、他3つは日本交通・日ノ丸自動車の共同運行。
;隣県から乗り入れるバス
* [[一畑バス]]（[[隠岐汽船]]接続バスが境港駅に乗り入れ。）
* [[松江市コミュニティバス]]（美保関コミュニティバス境港線と八束コミュニティバスが境港駅に乗り入れ。）
* [[安来市広域生活バス]]（イエローバス、米子駅に乗り入れ。）
* [[奥出雲交通]]（鳥上線が日南町の[[日南町#阿毘縁|阿毘縁]]に乗り入れ。）
* [[真庭市コミュニティバス]]（まにわくん♡、中曽・関金ルートが[[関金温泉]]に乗り入れ。）
* [[夢つばめ]]（新温泉町民バス、平日朝の片道1便のみ岩美駅に乗り入れ。）
; 県内バス輸送人員（年間）
* 2012年671万5000人
鳥取県は、全国で最もバスの利用者が少ない&lt;ref&gt;[http://www.pref.saitama.lg.jp/a0206/quiz/documents/20154syou.pdf タイトル不明（）]{{リンク切れ|date=2020年10月}}（[[埼玉県]]資料）&lt;/ref&gt;。

==== 道路 ====
島根県の松江市内に[[山陰自動車道|松江道路]]が開通した[[1998年]]（平成10年）[[4月17日]]以降、鳥取県は長らく「日本で唯一都道府県庁所在都市に[[高速道路]]がない県」であったが、[[2004年]]（平成16年）[[11月1日]]に[[山陰自動車道]][[青谷インターチェンジ]]のある[[青谷町]]を編入合併したため、解消された。
{{表2列|
* [[高速道路]]
** [[鳥取自動車道]]（[[智頭インターチェンジ|智頭]] - [[鳥取インターチェンジ|鳥取]]）
*** [[志戸坂峠道路]]（[[駒帰交差点|駒帰]] - 智頭、通称としての「鳥取道」に含まれる）
** [[米子自動車道]]（[[江府インターチェンジ|江府]] - [[米子ジャンクション|米子]]）
** [[山陰自動車道]]（鳥取 - [[はわいインターチェンジ|はわい]]、[[大栄東伯インターチェンジ|大栄東伯]] - [[米子西インターチェンジ|米子西]]）
** [[山陰近畿自動車道]]（[[福部インターチェンジ|福部]] - 七坂トンネル）
** [[北条湯原道路]]（[[北条インターチェンジ|北条]] - [[倉吉西インターチェンジ|倉吉西]]）
** [[江府三次道路]]（福長 - 霞）
* [[県道]]
{{see|鳥取県の県道一覧}}
|
* [[国道]]
** [[国道9号]]
** [[国道29号]]
** [[国道53号]]
** [[国道178号]]
** [[国道179号]]
** [[国道180号]]
** [[国道181号]]
** [[国道183号]]
** [[国道313号]]
** [[国道373号]]
** [[国道431号]]
** [[国道482号]]
}}

==== 空港・港 ====
; 空港
: 東部の[[鳥取空港]]、西部の[[美保飛行場|米子空港]]の2つの空港を持つ。
; 主な港
: 日本海側有数の[[漁港]]である[[境港 (港湾)|境港]]や、[[重要港湾]]の[[鳥取港]]などがある。

==== 自動車登録番号標 ====
*鳥取[[日本のナンバープレート|ナンバー]] - 県全域

=== 医療・福祉 ===
{{main|Category:鳥取県の医療機関}}
;[[災害拠点病院]]
* [[鳥取県災害拠点病院]]
;[[保育所]]
* [[鳥取県保育所一覧]]

== 教育 ==
;[[大学]]
[[国立大学|国立]]
* [[鳥取大学]]（[[鳥取市]]、[[米子市]]）
[[公立大学|公立]]
* [[公立鳥取環境大学]]（鳥取市）
[[私立大学|私立]]
* [[鳥取看護大学]]（[[倉吉市]]）
;[[短期大学]]
私立
* [[鳥取短期大学]]（倉吉市）
;[[通信制大学]]
私立
* [[放送大学]] 鳥取学習センター（鳥取市）
;[[高等専門学校]]
国立
* [[米子工業高等専門学校]]（米子市）
;[[専修学校]]
* [[鳥取県専修学校一覧]]
;[[特別支援学校]]
* [[鳥取県特別支援学校一覧]]
;[[高等学校]]
* [[鳥取県高等学校一覧]]
;[[中学校]]
* [[鳥取県中学校一覧]]
;[[小学校]]
* [[鳥取県小学校一覧]]
;[[幼稚園]]
* [[鳥取県幼稚園一覧]]
;その他教育機関
;[[農業大学校]]
* [[鳥取県立農業大学校]] [https://www.pref.tottori.lg.jp/noudai/]（倉吉市）

== マスメディア ==
=== 新聞 ===
;地方紙
* [[日本海新聞]]：鳥取県の[[地方紙]]。島根県東部・兵庫県北部でも販売されている。
* [[山陰中央新報]]：島根県の地方紙で、鳥取県西部の一部でも販売されている。
* [[中国新聞]]：[[広島県]]に本社を置く中国地方の[[ブロック紙]]。鳥取市に支局を持ち、1970年代までは鳥取版も存在したが現在では島根版がわずかに販売されているのみである。
;全国紙
:[[読売新聞]]、[[朝日新聞]]、[[毎日新聞]]には鳥取版がある。
:[[日本経済新聞]]、[[産経新聞]]は中国地方向けの地方版がある。「[[地方版]]」の項を参照されたい。

=== 放送 ===
{{鳥取県・島根県の放送|state=collapsed}}
鳥取県・島根県の県域民放各局は互いの県に乗り入れて放送を実施している。詳しくは、「[[電波相互乗り入れ#乗り入れの経緯とその後]]」の項目を参照されたい。局名の後の（ ）内は局所在地。
; [[日本放送協会|NHK]]
* [[NHK鳥取放送局]]（[[鳥取市]]） - [[NHK総合テレビジョン|総合テレビ]]と[[NHKラジオ第一放送|ラジオ第1]]で県域放送を実施。
** [[NHK米子支局]]（[[米子市]]）
;民放テレビ局
* [[山陰放送|BSSテレビ]]（BSS;[[米子市]]）：[[ジャパン・ニュース・ネットワーク|JNN]]（[[TBSテレビ|TBS]]）系列、メイン送信所は[[松江市]]、ラジオ兼営。山陰放送のテレビ局開局の経緯は[[山陰放送#テレビ放送開始とエリア拡大|こちらの当該項]]参照のこと。
* [[日本海テレビジョン放送|日本海テレビ]]（NKT;[[鳥取市]]）：[[日本ニュースネットワーク|NNN]]（[[日本テレビ放送網|日本テレビ]]）系列
**上記2社は通常時終夜放送を実施している。
* [[山陰中央テレビジョン放送|さんいん中央テレビ]]（TSK;[[松江市]]）：[[フジニュースネットワーク|FNN]]（[[フジテレビジョン|フジテレビ]]）系列
※山陰地方には、 [[オールニッポン・ニュースネットワーク|ANN]]（[[テレビ朝日]]）系列局や[[TXNネットワーク|TXN]]（[[テレビ東京]]）系列局などがないため、ケーブルテレビ経由で県外の系列局を視聴する形となっている{{efn|テレビ東京系は町内での受信ができないことを理由に同意が得られない岩美町、八頭町を除くCATV提供エリア全域で視聴可能。[[独立放送局]]は八頭町を除くCATV提供エリア全域で視聴可能。}}。なお、テレビ朝日系に関しては、[[キー局]]のテレビ朝日が取材拠点として[[テレビ朝日米子支局]]・[[テレビ朝日鳥取支局]]を置いている。
;AMラジオ
* [[山陰放送|BSSラジオ]]（BSS;[[米子市]]）：[[ジャパン・ラジオ・ネットワーク|JRN]]･[[全国ラジオネットワーク|NRN]]系列、メイン送信所は[[米子市]]、テレビ兼営。
;FMラジオ
* [[エフエム山陰]]（[[島根県]][[松江市]]） - [[全国FM放送協議会|JFN]]系列。
; [[ケーブルテレビ]]
{{see|Category:鳥取県のケーブルテレビ局}}
;[[コミュニティFM]]
* [[FM鳥取]]（[[鳥取市]]）
* [[DARAZコミュニティ放送]]（[[米子市]]）

== 文化・スポーツ ==
=== 方言 ===
鳥取県の[[方言]]は、東部・中部と西部で大きく異なる。東部（因幡）の[[因州弁]]・中部（東伯耆）の[[倉吉弁]]は、兵庫県の北部の[[但馬弁]]と共通した特徴を持ち、'''[[東山陰方言]]'''に分類されている。一方で、[[西伯耆方言|西部（西伯耆）の方言]]は島根県の東部の[[出雲弁]]と共通した特徴を持ち、'''[[雲伯方言]]'''に分類されている。

=== 食文化 ===
{{See also|Category:鳥取県の食文化}}
; 郷土料理
{{Main|日本の郷土料理一覧#鳥取県}}

=== 伝統工芸 ===
; [[経済産業大臣指定伝統的工芸品]]
* [[弓浜絣]]（[[織物]]、[[1975年]]）
* [[因州和紙]]（[[和紙]]、1975年）
* [[出雲石燈ろう]]（石工品・[[貴石]]細工、[[1976年]]）

; 伝統工芸品
{{Main|日本の伝統工芸品の一覧#鳥取県}}

=== 民話・伝説 ===
* [[投入堂]] - [[役小角]]が投げ入れたという言い伝えがある。
* [[多鯰ヶ池のおたね]]
* [[湖山長者]]
* [[桂蔵坊]]
* [[立見峠のおとんじょろう]]
* [[佐治谷ばなし]]
* [[人形峠のくも]]
* [[大山の背比べ]]
* [[幽霊滝の伝説|幽霊滝]]
* [[関金町|関金]]のえぐいも（[[空海]]の伝説）
* [[小泉八雲]]の新婚旅行（[[琴浦町]]）
* [[三朝温泉]]の白狼伝説

=== スポーツ ===
* [[鳥取県サッカーリーグ]]:トップリーグ、セカンドリーグ
* [[鳥取県女子サッカーリーグ]]
* [[鳥取県フットサルリーグ]]:男子、女子
* 鳥取県バスケットボールリーグ（TBL）:男子1部、男子2部、女子
* [[日本海バレーボールリーグ]]:男子1部、男子2部、女子
* 日本海ハンドボールリーグ
* 鳥取県ラグビーリーグ
;スポーツチーム
{{See also|Category:鳥取県のスポーツチーム}}
* [[ガイナーレ鳥取]]（サッカー）：[[日本プロサッカーリーグ|Jリーグ]]所属
* [[SC鳥取ドリームス]]（サッカー）：ガイナーレファミリー。[[中国サッカーリーグ]]所属
* [[鳥取キッカーズFC|鳥取KFC]]（サッカー）：鳥取県サッカーリーグ所属
* [[元気SC]]（サッカー）：鳥取県サッカーリーグ所属
* [[八頭クラブ]]（ホッケー）：西日本リーグ所属
* [[鳥取Pear Kings]]（硬式野球）
* [[ホワイトエンジェルス]]（女子軟式野球）：米子で活動する女子軟式チーム
* [[Cheerful鳥取]]（バドミントン）：[[バドミントン日本リーグ|日本リーグ]]所属
; 過去に存在したスポーツチーム
* [[オール鳥取]]（硬式[[野球]]）
* [[打吹クラブ]]（硬式野球）
* [[西日本旅客鉄道米子支社|米子鉄道管理局]]（硬式野球）：[[都市対抗野球大会]]県勢唯一の出場
* [[王子製紙米子硬式野球部|王子製紙米子]]（硬式野球）：[[王子硬式野球部|王子製紙春日井]]、[[王子製紙苫小牧硬式野球部|王子製紙苫小牧]]との統合により廃部
* [[米子コスモス]]（女子サッカー）

== 観光 ==
[[ファイル:Japan Tottori MitokuSan Nageiredo DSC01248.jpg|thumb|国宝 [[三仏寺]]投入堂]]
[[ファイル:Kurayoshi Utsubuki-Tamagawa46n4592.jpg|thumb|重伝建 [[打吹玉川]]]]
[[ファイル:浦富海岸、鴨ガ磯.jpg|thumb|名勝 [[浦富海岸]]]]
{{Main|鳥取県の観光地}}

=== 有形文化財建造物 ===
{{main|鳥取県指定文化財一覧}}
;[[国宝]]
* [[三仏寺]]：奥院（投入堂）
;[[重要伝統的建造物群保存地区]]
* [[打吹玉川]]（倉吉市）

=== 景勝地 ===
* [[鳥取砂丘]]
* [[浦富海岸]]
* [[岩井温泉]]
* [[浜村温泉]]
* [[三朝温泉]]
* [[皆生温泉]]
* [[はわい温泉]]
* [[大山 (鳥取県)|大山]]
* [[東郷湖]]

=== 史跡・社閣 ===
{{main|中国地方の史跡一覧#鳥取県|鳥取県の城}}
* [[鳥取城]]跡
* [[米子城]]跡
* [[若桜鬼ヶ城]]跡
* [[若桜宿]]
* [[不動院岩屋堂]]
* [[羽衣石城]]跡
* [[鹿野城]]跡
* [[智頭宿]]
* 三徳山三仏寺[[投入堂]]
* [[伯耆三十三観音霊場]]
* [[青谷横木遺跡]]

=== レジャー施設・観光施設・文化施設 ===
[[ファイル:Tottori Nijisseiki Pear Museum03s4592.jpg|thumb|[[鳥取二十世紀梨記念館]]]]
* [[倉吉パークスクエア]]
** [[鳥取二十世紀梨記念館]]
* [[わかさ氷ノ山自然ふれあいの里]]
** [[わかさ氷ノ山スキー場]]
** [[鳥取県立氷ノ山自然ふれあい館響の森]]
* [[水木しげるロード]]
* [[青山剛昌ふるさと館]]

=== 祭事・イベント ===
{{main|Category:鳥取県の祭り}}
* [[鳥取しゃんしゃん祭]]（鳥取市）- 山陰最大の観客数のある夏祭り。毎年、8月中旬に「しゃんしゃん傘」と呼ばれる傘を使って、約4,000人が中心市街地を踊る。
* [[米子がいな祭]]（米子市）
* [[みなと祭]]（境港市）
* [[SUN-IN未来ウオーク]] - 山陰最大級のウオーキングイベント。鳥取県は「ウオーキング立県とっとり」を掲げている。
* [[大山ミュージックリゾート]] - 複数年・広域的に行われた音楽イベント
* [[鳥取ロケ地映画祭]]（2007年）

=== 「星取県」 ===
鳥取商工会議所青年部が提唱し、2017年から使用している。夜間に人工の明かりが少なく、どの市町村からでも[[天の川]]が見えることや、鳥取市が星の見えやすさ日本一となったこと、また県が以前から使っている「蟹取県」にちなむ&lt;ref&gt;[http://www.pref.tottori.lg.jp/266985.htm 「星取県」って何？]鳥取県（2020年11月1日閲覧）&lt;/ref&gt;&lt;ref&gt;[http://www.asahi.com/articles/ASK4B55XGK4BPUUB00X.html 鳥取改め「星取県です」少ない街の明かり逆手にPR／柳川迅][[朝日新聞デジタル]]（2017年5月1日）2020年1月24日閲覧&lt;/ref&gt;。

これにちなんだブランド米「星空舞」の販売が2019年に始まった&lt;ref name="日経20191219"/&gt;。

== 対外関係 ==
=== 姉妹自治体・提携自治体 ===
==== 海外 ====
* {{Flagicon|CHN}}[[河北省]]（[[中華人民共和国]]）
** [[1986年]]（[[昭和]]61年）[[6月9日]]提携&lt;ref&gt;[http://www.clair.or.jp/j/exchange/shimai/data/detail/1291 協定書締結]&lt;/ref&gt;
* {{Flagicon|CHN}}[[吉林省]]（中華人民共和国）
** [[1994年]]（[[平成]]6年）[[9月2日]]提携&lt;ref&gt;[http://www.clair.or.jp/j/exchange/shimai/data/detail/1290 吉林省長春市にて友好交流覚書署名]&lt;/ref&gt;
* {{Flagicon|KOR}}[[江原特別自治道]]（[[大韓民国]]）
** [[1994年]]（[[平成]]6年）[[11月7日]]提携&lt;ref&gt;[http://www.clair.or.jp/j/exchange/shimai/data/detail/1292 協定書締結]&lt;/ref&gt;
* {{Flagicon|MNG}}[[トゥブ県]]（[[モンゴル国]]）
** [[1997年]]（[[平成]]9年）[[7月25日]]提携&lt;ref&gt;[http://www.clair.or.jp/j/exchange/shimai/data/detail/1293 鳥取県境港市にて友好交流覚書署名]&lt;/ref&gt;
* {{Flagicon|RUS}}[[沿海地方]]（[[ロシア連邦]]）
** [[2010年]]（[[平成]]22年）[[5月5日]]提携&lt;ref&gt;[http://www.clair.or.jp/j/exchange/shimai/data/detail/1294 ウラジオストク市における協定締結]&lt;/ref&gt;
* {{Flagicon|JAM}}[[ウェストモアランド教区]]（[[ジャマイカ|ジャマイカ国]]）
** [[2016年]]（[[平成]]28年）[[3月24日]]提携&lt;ref&gt;[http://www.clair.or.jp/j/exchange/shimai/data/detail/1709 姉妹提携に関する協力覚書署名]&lt;/ref&gt;
* {{Flagicon|USA}}[[バーモント州]]（[[アメリカ合衆国]]）
** [[2018年]]（[[平成]]30年）[[7月18日]]提携&lt;ref&gt;[http://www.clair.or.jp/j/exchange/shimai/data/detail/1748 姉妹提携協定書署名]&lt;/ref&gt;
* {{Flagicon|ROC}}[[台中市]]（[[中華民国]] [[台湾の行政区分#直轄市|直轄市]]）
** [[2018年]]（[[平成]]30年）[[11月2日]]提携

==== 国内 ====
* {{Flagicon|高知県}}[[高知県]]（[[四国地方]]）
** [[2013年]]（平成25年）[[3月24日]]提携&lt;ref&gt;[http://www.pref.tottori.lg.jp/238602.htm まんが王国とっとり公式ホームページ「まんが王国会議/高知県との連携」]&lt;/ref&gt;

== 鳥取県を舞台とした作品 ==
{{main|鳥取県を舞台とした作品一覧}}

;映画
* [[八岐之大蛇の逆襲]]（[[DAICON FILM]]（後の映像制作会社[[ガイナックス]]の母体となった自主制作集団）によって製作されたアマチュア映画。米子市が舞台となっている）：[[1984年]]
* [[男はつらいよ 寅次郎の告白]]（[[男はつらいよ]]シリーズ）：[[1991年]]
* [[リアリズムの宿]]（原作：[[つげ義春]]、[[映画監督|監督]]：[[山下敦弘]]）：[[2004年]]
* [[妖怪大戦争 (2005年の映画)|妖怪大戦争]]：[[2005年]]（2004年7月に鳥取ロケでクランクイン）
* [[銀色の雨]]（原作：[[浅田次郎]]、監督：[[鈴井貴之]]）：[[2009年]]（2008年11月～12月に米子市でクランクイン）
* [[恋谷橋]]：[[2011年]]

;小説・随想など
* [[暗夜行路]]（[[志賀直哉]]）
* [[鳥取のふとんの話]]（[[小泉八雲]]）
* [[幽霊滝の伝説]]（小泉八雲）
* [[のんのんばあとオレ]]（[[水木しげる]]）
* [[赤朽葉家の伝説]]（[[桜庭一樹]]）
* [[砂糖菓子の弾丸は撃ちぬけない]]（桜庭一樹）
* [[妖鬼海産都市　-ユメミナト-]]（谷山龍）

;漫画
* [[ガクラン放浪記]]（[[弘兼憲史]]） - [[鳥取県立米子東高等学校|米子東高校]]を中心とする米子市
* [[人間交差点]]（作･[[矢島正雄]]、画･弘兼憲史） - 米子東高校
* [[ハロー張りネズミ]]（弘兼憲史） - 米子東高校
* [[タッチ (漫画)|タッチ]]（[[あだち充]]） -  鳥取市民体育館、新袋川土手
* [[砂漠の野球部]]（[[コージィ城倉]]） - 鳥取市および[[鳥取砂丘]]
* [[父の暦]]（[[谷口ジロー]]） - 鳥取市・[[鳥取大火]]
* [[遙かな町へ]]（谷口ジロー） - 倉吉市
* [[のんのんばあとオレ]]（[[水木しげる]]） - 境港市
* [[ヒマチの嬢王]]（[[茅原クレセ]]） - 米子市朝日町

=== 鳥取県でロケが行われた作品 ===
[[ファイル:Enchoen02bs4592.jpg|thumb|『西遊記』ロケ地の[[燕趙園]]]]
* [[しあわせはどこに]]（主演:[[葉山良二]]、[[芦川いづみ]]。[[1956年]]）
* [[絶唱]]（[[1966年]]、[[1975年]]）
* [[砂の器]]（[[1962年]]、[[1974年]]、その他）
* [[八つ墓村 (1977年の映画)|八つ墓村]]（主演：[[萩原健一]]。[[1976年]]） - 峠から村を俯瞰するシーンを[[明地峠]]で撮影したほか、[[日野町 (鳥取県)|日野町]]ではクライマックスの炎上シーンを撮影した{{要出典|date=2014年9月}}&lt;!--多くのブログ等で言及されており、間違いはないのでしょうけども、[[WP:RS]]を文句なしに充足する水準の出典があるとは言えないのでひとまず。--&gt;&lt;ref&gt;[http://www.jimovie.co.jp/八つ墓村.html 地ムービー 八つ墓村]{{リンク切れ|date=2020年1月}}2014年9月5日閲覧。&lt;/ref&gt;。
* [[心はいつもラムネ色]]（[[1984年]]）
* [[夢千代日記]]（主演：[[吉永小百合]]。[[1985年]]）
* [[太陽の犬]]（[[1988年]]）
* [[未来日記 (ウンナンのホントコ!)|未来日記]]（未来日記劇場版。[[2000年]]）
* [[西遊記 (2006年のテレビドラマ)|西遊記]]（[[フジテレビ]]・[[香取慎吾]]版、[[2006年]]） - [[燕趙園]]
* [[琴浦さん]]（[[2013年]]）
* [[こども刑事めめたん]]（[[2015年]]） - 鳥取県も制作参加した作品。
* [[宇崎ちゃんは遊びたい!]]（2020年、[[ENGI]]） - 第9話・第10話が鳥取県が舞台となっており、監修協力に鳥取県がクレジットされている。劇中には[[平井伸治]]をモデルとした鳥取県知事（声：[[山根雅史]]）が登場している。

== 鳥取県出身の人物 ==
{{Main|鳥取県出身の人物一覧}}

==その他==
[[小惑星]][[鳥取_(小惑星)|(4720) Tottori]]は鳥取に因んで命名された&lt;ref&gt;{{cite web|url=https://www.minorplanetcenter.net/db_search/show_object?object_id=4720 |title=(4720) Tottori = 1940 XF = 1948 CD = 1973 SH5 = 1978 EU4 = 1982 JL4 = 1986 PY3 = 1988 EY2 = 1990 YG|accessdate=2022-07-03}}&lt;/ref&gt;。

== 脚注 ==
{{脚注ヘルプ}}
=== 注釈 ===
{{Notelist}}
=== 出典 ===
{{Reflist|2}}

== 関連項目 ==
* [[鳥取県の県道一覧]]
* [[鳥取県高等学校一覧]]
* [[鳥取県出身の人物一覧]]
* [[鳥取県人権侵害救済推進及び手続に関する条例]]
* [[鳥取県の観光地]]
* [[鳥取県の島の一覧]]
* [[日本の地方公共団体一覧]]
* [[日本の地理]]、[[日本の地域]]
* [[すなば珈琲]]

== 外部リンク ==

{{ウィキポータルリンク|日本の都道府県/鳥取県|{{Flagicon|鳥取県|size=36px}}|36px|Portal:日本の都道府県/鳥取県}}
{{Multimedia|鳥取県の画像}}
{{Sisterlinks
|commons=鳥取県
|commonscat=Tottori prefecture
|q=no
|v=no
|voy=Tottori
}}
* 行政
** {{Official website}}
** {{Twitter|tottori_kouhou|鳥取県広報課}}
** {{Facebook|tottori.pref.kouhou|鳥取県広報課}}
* 観光
** [https://www.tottori-guide.jp/ 鳥取県観光案内 とっとり旅の生情報] - 鳥取県観光連盟
* 地図
** {{Osmrelation|3285636}}
** [http://geoshape.ex.nii.ac.jp/city/code/?鳥取県 鳥取県 | 歴史的行政区域データセットβ版] - Geoshapeリポジトリ（&lt;small&gt;左側基準年月日のチェック操作で&lt;/small&gt;行政区域の変遷を見ることができる）

{{s-start}}
{{s-bef|before=[[鳥取藩]]|表記=前}}
{{s-ttl|title=行政区の変遷
|years=[[1871年]] -|years2=}}
{{s-aft|after=-----|表記=次}}
{{end}}
{{日本の都道府県}}
{{鳥取県の自治体}}
{{鳥取県の郡}}
{{Normdaten}}

{{デフォルトソート:とつとりけん}}
[[Category:日本の都道府県]]
[[Category:鳥取県|*]]</text>
      <sha1>tqh54hk5tt8hjan0wxa4bv47oecgebm</sha1>
    </revision>
  </page>
  